{"battles":219535,"avg":0.66,"pokemon":[{"name":"Iron Hands","usage":46.55219,"raw":193849,"rawp":44.15,"real":110066,"realp":53.871},{"name":"Flutter Mane","usage":43.14658,"raw":181327,"rawp":41.298,"real":85252,"realp":41.726},{"name":"Urshifu-Rapid-Strike","usage":39.08743,"raw":157059,"rawp":35.771,"real":82124,"realp":40.195},{"name":"Tornadus","usage":33.64569,"raw":141590,"rawp":32.248,"real":45698,"realp":22.367},{"name":"Landorus-Therian","usage":29.829,"raw":125036,"rawp":28.477,"real":63538,"realp":31.098},{"name":"Rillaboom","usage":29.05093,"raw":119476,"rawp":27.211,"real":59192,"realp":28.971},{"name":"Arcanine-Hisui","usage":27.97266,"raw":117531,"rawp":26.768,"real":60486,"realp":29.605},{"name":"Gholdengo","usage":25.03731,"raw":96350,"rawp":21.944,"real":43720,"realp":21.398},{"name":"Heatran","usage":24.4795,"raw":95352,"rawp":21.717,"real":47333,"realp":23.167},{"name":"Amoonguss","usage":22.28607,"raw":86510,"rawp":19.703,"real":40579,"realp":19.861},{"name":"Chien-Pao","usage":19.98923,"raw":84939,"rawp":19.345,"real":38072,"realp":18.634},{"name":"Ogerpon-Wellspring","usage":19.42552,"raw":82959,"rawp":18.894,"real":39329,"realp":19.249},{"name":"Roaring Moon","usage":17.63984,"raw":70237,"rawp":15.997,"real":27522,"realp":13.47},{"name":"Farigiraf","usage":12.13453,"raw":49975,"rawp":11.382,"real":16721,"realp":8.184},{"name":"Ogerpon-Hearthflame","usage":11.46988,"raw":49226,"rawp":11.211,"real":23260,"realp":11.384},{"name":"Chi-Yu","usage":10.42548,"raw":45683,"rawp":10.404,"real":21330,"realp":10.44},{"name":"Urshifu","usage":9.00093,"raw":34470,"rawp":7.851,"real":16581,"realp":8.115},{"name":"Iron Bundle","usage":8.54058,"raw":38021,"rawp":8.659,"real":15397,"realp":7.536},{"name":"Kingambit","usage":8.0189,"raw":33917,"rawp":7.725,"real":14061,"realp":6.882},{"name":"Dragonite","usage":7.9818,"raw":35176,"rawp":8.011,"real":16546,"realp":8.098},{"name":"Indeedee-F","usage":7.93622,"raw":36596,"rawp":8.335,"real":16952,"realp":8.297},{"name":"Sinistcha","usage":7.82491,"raw":43224,"rawp":9.844,"real":21328,"realp":10.439},{"name":"Ursaluna-Bloodmoon","usage":7.59598,"raw":33923,"rawp":7.726,"real":18752,"realp":9.178},{"name":"Dondozo","usage":5.97596,"raw":22440,"rawp":5.111,"real":12153,"realp":5.948},{"name":"Armarouge","usage":5.94429,"raw":26351,"rawp":6.002,"real":13901,"realp":6.804},{"name":"Ninetales-Alola","usage":5.57279,"raw":27404,"rawp":6.241,"real":10635,"realp":5.205},{"name":"Torkoal","usage":4.87842,"raw":22940,"rawp":5.225,"real":12437,"realp":6.087},{"name":"Cresselia","usage":4.83451,"raw":23048,"rawp":5.249,"real":9526,"realp":4.662},{"name":"Ursaluna","usage":4.46727,"raw":18752,"rawp":4.271,"real":9600,"realp":4.699},{"name":"Tatsugiri","usage":4.33504,"raw":16745,"rawp":3.814,"real":10126,"realp":4.956},{"name":"Regidrago","usage":4.20032,"raw":16199,"rawp":3.689,"real":7939,"realp":3.886},{"name":"Glimmora","usage":3.63486,"raw":13158,"rawp":2.997,"real":5243,"realp":2.566},{"name":"Salamence","usage":3.46365,"raw":14190,"rawp":3.232,"real":6811,"realp":3.334},{"name":"Grimmsnarl","usage":3.38966,"raw":18309,"rawp":4.17,"real":7473,"realp":3.658},{"name":"Weezing","usage":3.3691,"raw":14777,"rawp":3.366,"real":5997,"realp":2.935},{"name":"Dusclops","usage":3.2015,"raw":13753,"rawp":3.132,"real":5474,"realp":2.679},{"name":"Ogerpon","usage":3.08591,"raw":13603,"rawp":3.098,"real":5623,"realp":2.752},{"name":"Landorus","usage":2.97485,"raw":11818,"rawp":2.692,"real":6159,"realp":3.014},{"name":"Clefairy","usage":2.831,"raw":15006,"rawp":3.418,"real":6883,"realp":3.369},{"name":"Ogerpon-Cornerstone","usage":2.82933,"raw":12022,"rawp":2.738,"real":5062,"realp":2.478},{"name":"Brambleghast","usage":2.6115,"raw":8998,"rawp":2.049,"real":4609,"realp":2.256},{"name":"Pelipper","usage":2.49994,"raw":11662,"rawp":2.656,"real":4929,"realp":2.412},{"name":"Baxcalibur","usage":2.34088,"raw":11999,"rawp":2.733,"real":5695,"realp":2.787},{"name":"Kommo-o","usage":2.29063,"raw":12630,"rawp":2.877,"real":5072,"realp":2.482},{"name":"Regieleki","usage":2.02684,"raw":11844,"rawp":2.698,"real":4784,"realp":2.341},{"name":"Gastrodon","usage":1.96274,"raw":9374,"rawp":2.135,"real":4080,"realp":1.997},{"name":"Lilligant-Hisui","usage":1.8514,"raw":8261,"rawp":1.881,"real":2367,"realp":1.159},{"name":"Milotic","usage":1.65147,"raw":9605,"rawp":2.188,"real":3532,"realp":1.729},{"name":"Volcarona","usage":1.6365,"raw":8033,"rawp":1.83,"real":3160,"realp":1.547},{"name":"Annihilape","usage":1.53942,"raw":9359,"rawp":2.132,"real":4204,"realp":2.058},{"name":"Goodra-Hisui","usage":1.51184,"raw":7812,"rawp":1.779,"real":3612,"realp":1.768},{"name":"Moltres-Galar","usage":1.47384,"raw":7378,"rawp":1.68,"real":3091,"realp":1.513},{"name":"Dragapult","usage":1.43533,"raw":7338,"rawp":1.671,"real":3484,"realp":1.705},{"name":"Tyranitar","usage":1.3448,"raw":8649,"rawp":1.97,"real":3975,"realp":1.946},{"name":"Gothitelle","usage":1.3289,"raw":6728,"rawp":1.532,"real":2552,"realp":1.249},{"name":"Okidogi","usage":1.31953,"raw":6373,"rawp":1.451,"real":2803,"realp":1.372},{"name":"Gyarados","usage":1.27516,"raw":6784,"rawp":1.545,"real":3079,"realp":1.507},{"name":"Thundurus-Therian","usage":1.06947,"raw":5450,"rawp":1.241,"real":2375,"realp":1.162},{"name":"Enamorus-Therian","usage":1.04346,"raw":4567,"rawp":1.04,"real":2444,"realp":1.196},{"name":"Empoleon","usage":0.9168,"raw":7240,"rawp":1.649,"real":3138,"realp":1.536},{"name":"Gallade","usage":0.88403,"raw":3504,"rawp":0.798,"real":1676,"realp":0.82},{"name":"Thundurus","usage":0.8827,"raw":5665,"rawp":1.29,"real":1750,"realp":0.857},{"name":"Scream Tail","usage":0.87183,"raw":4330,"rawp":0.986,"real":1674,"realp":0.819},{"name":"Basculegion","usage":0.82202,"raw":4195,"rawp":0.955,"real":2241,"realp":1.097},{"name":"Oranguru","usage":0.81718,"raw":4311,"rawp":0.982,"real":1749,"realp":0.856},{"name":"Maushold","usage":0.76019,"raw":4302,"rawp":0.98,"real":1637,"realp":0.801},{"name":"Arcanine","usage":0.68124,"raw":4650,"rawp":1.059,"real":2240,"realp":1.096},{"name":"Zapdos-Galar","usage":0.66788,"raw":3439,"rawp":0.783,"real":1510,"realp":0.739},{"name":"Sneasler","usage":0.65575,"raw":4520,"rawp":1.029,"real":2144,"realp":1.049},{"name":"Ting-Lu","usage":0.63705,"raw":4039,"rawp":0.92,"real":1797,"realp":0.88},{"name":"Hatterene","usage":0.59484,"raw":3281,"rawp":0.747,"real":1298,"realp":0.635},{"name":"Sableye","usage":0.58294,"raw":4449,"rawp":1.013,"real":1640,"realp":0.803},{"name":"Sylveon","usage":0.56618,"raw":3447,"rawp":0.785,"real":1652,"realp":0.809},{"name":"Scizor","usage":0.49923,"raw":3951,"rawp":0.9,"real":1680,"realp":0.822},{"name":"Munkidori","usage":0.49237,"raw":2791,"rawp":0.636,"real":1262,"realp":0.618},{"name":"Politoed","usage":0.46526,"raw":2942,"rawp":0.67,"real":1370,"realp":0.671},{"name":"Talonflame","usage":0.44393,"raw":2733,"rawp":0.622,"real":903,"realp":0.442},{"name":"Zapdos","usage":0.4416,"raw":2623,"rawp":0.597,"real":1030,"realp":0.504},{"name":"Palafin","usage":0.4391,"raw":2900,"rawp":0.66,"real":1402,"realp":0.686},{"name":"Garchomp","usage":0.428,"raw":2940,"rawp":0.67,"real":1461,"realp":0.715},{"name":"Tinkaton","usage":0.41201,"raw":2304,"rawp":0.525,"real":941,"realp":0.461},{"name":"Articuno-Galar","usage":0.41171,"raw":2253,"rawp":0.513,"real":771,"realp":0.377},{"name":"Snorlax","usage":0.4037,"raw":3613,"rawp":0.823,"real":1147,"realp":0.561},{"name":"Staraptor","usage":0.37362,"raw":1511,"rawp":0.344,"real":591,"realp":0.289},{"name":"Weezing-Galar","usage":0.35979,"raw":2158,"rawp":0.491,"real":707,"realp":0.346},{"name":"Azumarill","usage":0.34294,"raw":2449,"rawp":0.558,"real":1169,"realp":0.572},{"name":"Bronzong","usage":0.33099,"raw":1645,"rawp":0.375,"real":538,"realp":0.263},{"name":"Mamoswine","usage":0.32414,"raw":1865,"rawp":0.425,"real":963,"realp":0.471},{"name":"Corviknight","usage":0.31936,"raw":2329,"rawp":0.53,"real":938,"realp":0.459},{"name":"Fezandipiti","usage":0.31357,"raw":2480,"rawp":0.565,"real":914,"realp":0.447},{"name":"Hydreigon","usage":0.31189,"raw":2006,"rawp":0.457,"real":811,"realp":0.397},{"name":"Illumise","usage":0.3062,"raw":1554,"rawp":0.354,"real":424,"realp":0.208},{"name":"Spectrier","usage":0.29117,"raw":1951,"rawp":0.444,"real":881,"realp":0.431},{"name":"Murkrow","usage":0.27889,"raw":2319,"rawp":0.528,"real":698,"realp":0.342},{"name":"Wo-Chien","usage":0.25487,"raw":1701,"rawp":0.387,"real":777,"realp":0.38},{"name":"Iron Valiant","usage":0.25403,"raw":1769,"rawp":0.403,"real":794,"realp":0.389},{"name":"Great Tusk","usage":0.24094,"raw":1735,"rawp":0.395,"real":796,"realp":0.39},{"name":"Ceruledge","usage":0.22641,"raw":2517,"rawp":0.573,"real":1165,"realp":0.57},{"name":"Toxapex","usage":0.22391,"raw":1502,"rawp":0.342,"real":667,"realp":0.326},{"name":"Rotom-Wash","usage":0.22291,"raw":1299,"rawp":0.296,"real":602,"realp":0.295},{"name":"Chandelure","usage":0.21999,"raw":1546,"rawp":0.352,"real":616,"realp":0.301},{"name":"Zoroark-Hisui","usage":0.21651,"raw":1711,"rawp":0.39,"real":494,"realp":0.242},{"name":"Glastrier","usage":0.21495,"raw":1966,"rawp":0.448,"real":1006,"realp":0.492},{"name":"Garganacl","usage":0.21231,"raw":2525,"rawp":0.575,"real":1174,"realp":0.575},{"name":"Shiftry","usage":0.20578,"raw":1615,"rawp":0.368,"real":740,"realp":0.362},{"name":"Iron Moth","usage":0.20514,"raw":2030,"rawp":0.462,"real":881,"realp":0.431},{"name":"Flamigo","usage":0.20367,"raw":1337,"rawp":0.305,"real":698,"realp":0.342},{"name":"Sandy Shocks","usage":0.20036,"raw":1076,"rawp":0.245,"real":434,"realp":0.212},{"name":"Brute Bonnet","usage":0.19606,"raw":1654,"rawp":0.377,"real":677,"realp":0.331},{"name":"Enamorus","usage":0.18556,"raw":1585,"rawp":0.361,"real":750,"realp":0.367},{"name":"Bruxish","usage":0.1796,"raw":809,"rawp":0.184,"real":248,"realp":0.121},{"name":"Mimikyu","usage":0.17688,"raw":1241,"rawp":0.283,"real":456,"realp":0.223},{"name":"Houndstone","usage":0.17583,"raw":1275,"rawp":0.29,"real":624,"realp":0.305},{"name":"Meowscarada","usage":0.17313,"raw":1426,"rawp":0.325,"real":637,"realp":0.312},{"name":"Iron Jugulis","usage":0.14728,"raw":925,"rawp":0.211,"real":296,"realp":0.145},{"name":"Tauros-Paldea-Blaze","usage":0.14112,"raw":1384,"rawp":0.315,"real":624,"realp":0.305},{"name":"Ninetales","usage":0.13434,"raw":1364,"rawp":0.311,"real":579,"realp":0.283},{"name":"Typhlosion-Hisui","usage":0.13189,"raw":1013,"rawp":0.231,"real":438,"realp":0.214},{"name":"Kleavor","usage":0.12349,"raw":1129,"rawp":0.257,"real":486,"realp":0.238},{"name":"Tsareena","usage":0.12147,"raw":785,"rawp":0.179,"real":323,"realp":0.158},{"name":"Cetitan","usage":0.11704,"raw":1129,"rawp":0.257,"real":400,"realp":0.196},{"name":"Breloom","usage":0.115,"raw":1012,"rawp":0.23,"real":473,"realp":0.232},{"name":"Gliscor","usage":0.11492,"raw":1639,"rawp":0.373,"real":701,"realp":0.343},{"name":"Espathra","usage":0.0992,"raw":715,"rawp":0.163,"real":346,"realp":0.169},{"name":"Golem-Alola","usage":0.09332,"raw":871,"rawp":0.198,"real":436,"realp":0.213},{"name":"Skeledirge","usage":0.093,"raw":1045,"rawp":0.238,"real":458,"realp":0.224},{"name":"Clodsire","usage":0.08842,"raw":804,"rawp":0.183,"real":350,"realp":0.171},{"name":"Abomasnow","usage":0.08271,"raw":830,"rawp":0.189,"real":371,"realp":0.182},{"name":"Indeedee","usage":0.08077,"raw":448,"rawp":0.102,"real":262,"realp":0.128},{"name":"Umbreon","usage":0.07996,"raw":664,"rawp":0.151,"real":244,"realp":0.119},{"name":"Drifblim","usage":0.07904,"raw":480,"rawp":0.109,"real":163,"realp":0.08},{"name":"Gardevoir","usage":0.07859,"raw":611,"rawp":0.139,"real":203,"realp":0.099},{"name":"Clefable","usage":0.07857,"raw":664,"rawp":0.151,"real":238,"realp":0.116},{"name":"Pawmot","usage":0.07821,"raw":759,"rawp":0.173,"real":384,"realp":0.188},{"name":"Ludicolo","usage":0.07714,"raw":615,"rawp":0.14,"real":322,"realp":0.158},{"name":"Charizard","usage":0.07565,"raw":980,"rawp":0.223,"real":402,"realp":0.197},{"name":"Torterra","usage":0.07508,"raw":995,"rawp":0.227,"real":458,"realp":0.224},{"name":"Tauros-Paldea-Aqua","usage":0.07485,"raw":708,"rawp":0.161,"real":305,"realp":0.149},{"name":"Rotom-Heat","usage":0.07376,"raw":599,"rawp":0.136,"real":250,"realp":0.122},{"name":"Dipplin","usage":0.07319,"raw":1005,"rawp":0.229,"real":354,"realp":0.173},{"name":"Vikavolt","usage":0.07174,"raw":571,"rawp":0.13,"real":258,"realp":0.126},{"name":"Dragalge","usage":0.06876,"raw":399,"rawp":0.091,"real":208,"realp":0.102},{"name":"Slowbro","usage":0.06824,"raw":615,"rawp":0.14,"real":187,"realp":0.092},{"name":"Articuno","usage":0.06793,"raw":688,"rawp":0.157,"real":281,"realp":0.138},{"name":"Overqwil","usage":0.06741,"raw":722,"rawp":0.164,"real":376,"realp":0.184},{"name":"Klefki","usage":0.06529,"raw":773,"rawp":0.176,"real":256,"realp":0.125},{"name":"Dachsbun","usage":0.06471,"raw":587,"rawp":0.134,"real":234,"realp":0.115},{"name":"Conkeldurr","usage":0.06438,"raw":728,"rawp":0.166,"real":372,"realp":0.182},{"name":"Slaking","usage":0.06414,"raw":771,"rawp":0.176,"real":312,"realp":0.153},{"name":"Muk-Alola","usage":0.0632,"raw":435,"rawp":0.099,"real":197,"realp":0.096},{"name":"Iron Treads","usage":0.0629,"raw":506,"rawp":0.115,"real":248,"realp":0.121},{"name":"Samurott-Hisui","usage":0.06205,"raw":760,"rawp":0.173,"real":318,"realp":0.156},{"name":"Infernape","usage":0.05951,"raw":724,"rawp":0.165,"real":295,"realp":0.144},{"name":"Mienshao","usage":0.05824,"raw":667,"rawp":0.152,"real":265,"realp":0.13},{"name":"Gengar","usage":0.05775,"raw":738,"rawp":0.168,"real":394,"realp":0.193},{"name":"Magnezone","usage":0.05555,"raw":463,"rawp":0.105,"real":208,"realp":0.102},{"name":"Pincurchin","usage":0.0554,"raw":621,"rawp":0.141,"real":298,"realp":0.146},{"name":"Tornadus-Therian","usage":0.0544,"raw":254,"rawp":0.058,"real":116,"realp":0.057},{"name":"Rabsca","usage":0.05373,"raw":621,"rawp":0.141,"real":242,"realp":0.118},{"name":"Krookodile","usage":0.05228,"raw":414,"rawp":0.094,"real":164,"realp":0.08},{"name":"Orthworm","usage":0.05225,"raw":501,"rawp":0.114,"real":234,"realp":0.115},{"name":"Pikachu","usage":0.05082,"raw":273,"rawp":0.062,"real":104,"realp":0.051},{"name":"Wyrdeer","usage":0.05074,"raw":534,"rawp":0.122,"real":218,"realp":0.107},{"name":"Moltres","usage":0.05021,"raw":365,"rawp":0.083,"real":162,"realp":0.079},{"name":"Lycanroc","usage":0.04889,"raw":353,"rawp":0.08,"real":164,"realp":0.08},{"name":"Spiritomb","usage":0.04876,"raw":357,"rawp":0.081,"real":96,"realp":0.047},{"name":"Jumpluff","usage":0.04783,"raw":269,"rawp":0.061,"real":107,"realp":0.052},{"name":"Toxtricity","usage":0.04769,"raw":387,"rawp":0.088,"real":199,"realp":0.097},{"name":"Salazzle","usage":0.04553,"raw":330,"rawp":0.075,"real":150,"realp":0.073},{"name":"Lurantis","usage":0.04426,"raw":492,"rawp":0.112,"real":217,"realp":0.106},{"name":"Raichu","usage":0.04402,"raw":533,"rawp":0.121,"real":236,"realp":0.116},{"name":"Iron Thorns","usage":0.0416,"raw":454,"rawp":0.103,"real":203,"realp":0.099},{"name":"Lucario","usage":0.04101,"raw":473,"rawp":0.108,"real":208,"realp":0.102},{"name":"Volbeat","usage":0.03942,"raw":349,"rawp":0.079,"real":129,"realp":0.063},{"name":"Toxicroak","usage":0.03925,"raw":448,"rawp":0.102,"real":279,"realp":0.137},{"name":"Mandibuzz","usage":0.03811,"raw":254,"rawp":0.058,"real":79,"realp":0.039},{"name":"Scovillain","usage":0.03771,"raw":277,"rawp":0.063,"real":108,"realp":0.053},{"name":"Braviary","usage":0.03681,"raw":233,"rawp":0.053,"real":126,"realp":0.062},{"name":"Toedscruel","usage":0.03672,"raw":391,"rawp":0.089,"real":174,"realp":0.085},{"name":"Perrserker","usage":0.0362,"raw":212,"rawp":0.048,"real":96,"realp":0.047},{"name":"Bellibolt","usage":0.03577,"raw":423,"rawp":0.096,"real":192,"realp":0.094},{"name":"Braviary-Hisui","usage":0.03566,"raw":351,"rawp":0.08,"real":127,"realp":0.062},{"name":"Luxray","usage":0.03519,"raw":280,"rawp":0.064,"real":122,"realp":0.06},{"name":"Slither Wing","usage":0.0346,"raw":328,"rawp":0.075,"real":137,"realp":0.067},{"name":"Frosmoth","usage":0.03418,"raw":394,"rawp":0.09,"real":191,"realp":0.093},{"name":"Kilowattrel","usage":0.03375,"raw":565,"rawp":0.129,"real":224,"realp":0.11},{"name":"Pachirisu","usage":0.03204,"raw":302,"rawp":0.069,"real":80,"realp":0.039},{"name":"Glaceon","usage":0.03144,"raw":284,"rawp":0.065,"real":154,"realp":0.075},{"name":"Quaquaval","usage":0.03133,"raw":379,"rawp":0.086,"real":189,"realp":0.093},{"name":"Hariyama","usage":0.03073,"raw":586,"rawp":0.133,"real":259,"realp":0.127},{"name":"Mudsdale","usage":0.03059,"raw":275,"rawp":0.063,"real":126,"realp":0.062},{"name":"Grafaiai","usage":0.03055,"raw":553,"rawp":0.126,"real":240,"realp":0.117},{"name":"Revavroom","usage":0.03052,"raw":263,"rawp":0.06,"real":111,"realp":0.054},{"name":"Vivillon","usage":0.03049,"raw":233,"rawp":0.053,"real":82,"realp":0.04},{"name":"Greninja","usage":0.03021,"raw":378,"rawp":0.086,"real":168,"realp":0.082},{"name":"Uxie","usage":0.02977,"raw":289,"rawp":0.066,"real":111,"realp":0.054},{"name":"Qwilfish-Hisui","usage":0.02935,"raw":137,"rawp":0.031,"real":57,"realp":0.028},{"name":"Stonjourner","usage":0.02911,"raw":261,"rawp":0.059,"real":97,"realp":0.047},{"name":"Noivern","usage":0.0287,"raw":405,"rawp":0.092,"real":166,"realp":0.081},{"name":"Rotom-Mow","usage":0.02822,"raw":146,"rawp":0.033,"real":54,"realp":0.026},{"name":"Charjabug","usage":0.02775,"raw":491,"rawp":0.112,"real":216,"realp":0.106},{"name":"Arboliva","usage":0.02774,"raw":436,"rawp":0.099,"real":180,"realp":0.088},{"name":"Chesnaught","usage":0.02755,"raw":220,"rawp":0.05,"real":78,"realp":0.038},{"name":"Ribombee","usage":0.02657,"raw":417,"rawp":0.095,"real":183,"realp":0.09},{"name":"Ditto","usage":0.02654,"raw":319,"rawp":0.073,"real":145,"realp":0.071},{"name":"Ambipom","usage":0.0262,"raw":423,"rawp":0.096,"real":177,"realp":0.087},{"name":"Crawdaunt","usage":0.02612,"raw":276,"rawp":0.063,"real":135,"realp":0.066},{"name":"Electrode-Hisui","usage":0.02497,"raw":304,"rawp":0.069,"real":121,"realp":0.059},{"name":"Trevenant","usage":0.02473,"raw":292,"rawp":0.067,"real":84,"realp":0.041},{"name":"Goodra","usage":0.02449,"raw":199,"rawp":0.045,"real":85,"realp":0.042},{"name":"Slowking","usage":0.02432,"raw":206,"rawp":0.047,"real":74,"realp":0.036},{"name":"Persian-Alola","usage":0.02422,"raw":267,"rawp":0.061,"real":150,"realp":0.073},{"name":"Weavile","usage":0.02393,"raw":274,"rawp":0.062,"real":105,"realp":0.051},{"name":"Alomomola","usage":0.0235,"raw":177,"rawp":0.04,"real":83,"realp":0.041},{"name":"Decidueye-Hisui","usage":0.02313,"raw":254,"rawp":0.058,"real":114,"realp":0.056},{"name":"Cinderace","usage":0.0218,"raw":300,"rawp":0.068,"real":148,"realp":0.072},{"name":"Azelf","usage":0.02149,"raw":242,"rawp":0.055,"real":88,"realp":0.043},{"name":"Eiscue","usage":0.02104,"raw":139,"rawp":0.032,"real":52,"realp":0.025},{"name":"Basculegion-F","usage":0.02082,"raw":212,"rawp":0.048,"real":90,"realp":0.044},{"name":"Gothorita","usage":0.02068,"raw":266,"rawp":0.061,"real":86,"realp":0.042},{"name":"Slowking-Galar","usage":0.02066,"raw":350,"rawp":0.08,"real":135,"realp":0.066},{"name":"Oricorio-Sensu","usage":0.02025,"raw":349,"rawp":0.079,"real":173,"realp":0.085},{"name":"Vaporeon","usage":0.02013,"raw":245,"rawp":0.056,"real":99,"realp":0.048},{"name":"Sandslash-Alola","usage":0.02004,"raw":260,"rawp":0.059,"real":107,"realp":0.052},{"name":"Florges","usage":0.01991,"raw":369,"rawp":0.084,"real":153,"realp":0.075},{"name":"Slowbro-Galar","usage":0.01978,"raw":254,"rawp":0.058,"real":113,"realp":0.055},{"name":"Altaria","usage":0.01918,"raw":249,"rawp":0.057,"real":79,"realp":0.039},{"name":"Avalugg","usage":0.01914,"raw":134,"rawp":0.031,"real":52,"realp":0.025},{"name":"Barraskewda","usage":0.01899,"raw":193,"rawp":0.044,"real":91,"realp":0.045},{"name":"Dudunsparce","usage":0.01827,"raw":354,"rawp":0.081,"real":137,"realp":0.067},{"name":"Poliwrath","usage":0.01824,"raw":243,"rawp":0.055,"real":110,"realp":0.054},{"name":"Lilligant","usage":0.01811,"raw":250,"rawp":0.057,"real":85,"realp":0.042},{"name":"Cyclizar","usage":0.018,"raw":249,"rawp":0.057,"real":96,"realp":0.047},{"name":"Hippowdon","usage":0.01744,"raw":280,"rawp":0.064,"real":132,"realp":0.065},{"name":"Cryogonal","usage":0.01743,"raw":89,"rawp":0.02,"real":32,"realp":0.016},{"name":"Arbok","usage":0.01682,"raw":192,"rawp":0.044,"real":71,"realp":0.035},{"name":"Bisharp","usage":0.01642,"raw":361,"rawp":0.082,"real":229,"realp":0.112},{"name":"Avalugg-Hisui","usage":0.01602,"raw":210,"rawp":0.048,"real":92,"realp":0.045},{"name":"Espeon","usage":0.01594,"raw":350,"rawp":0.08,"real":137,"realp":0.067},{"name":"Floatzel","usage":0.01591,"raw":173,"rawp":0.039,"real":93,"realp":0.046},{"name":"Inteleon","usage":0.01591,"raw":292,"rawp":0.067,"real":146,"realp":0.071},{"name":"Medicham","usage":0.01555,"raw":177,"rawp":0.04,"real":67,"realp":0.033},{"name":"Delphox","usage":0.01554,"raw":246,"rawp":0.056,"real":67,"realp":0.033},{"name":"Yanmega","usage":0.01554,"raw":192,"rawp":0.044,"real":78,"realp":0.038},{"name":"Magcargo","usage":0.01512,"raw":121,"rawp":0.028,"real":57,"realp":0.028},{"name":"Jolteon","usage":0.01459,"raw":288,"rawp":0.066,"real":125,"realp":0.061},{"name":"Zorua-Hisui","usage":0.01457,"raw":75,"rawp":0.017,"real":38,"realp":0.019},{"name":"Cloyster","usage":0.01243,"raw":266,"rawp":0.061,"real":110,"realp":0.054},{"name":"Misdreavus","usage":0.01182,"raw":92,"rawp":0.021,"real":30,"realp":0.015},{"name":"Golduck","usage":0.01167,"raw":176,"rawp":0.04,"real":53,"realp":0.026},{"name":"Forretress","usage":0.01117,"raw":181,"rawp":0.041,"real":85,"realp":0.042},{"name":"Appletun","usage":0.01105,"raw":196,"rawp":0.045,"real":85,"realp":0.042},{"name":"Victreebel","usage":0.011,"raw":123,"rawp":0.028,"real":47,"realp":0.023},{"name":"Haxorus","usage":0.01094,"raw":237,"rawp":0.054,"real":104,"realp":0.051},{"name":"Drednaw","usage":0.01092,"raw":190,"rawp":0.043,"real":85,"realp":0.042},{"name":"Hawlucha","usage":0.01057,"raw":120,"rawp":0.027,"real":66,"realp":0.032},{"name":"Chansey","usage":0.01049,"raw":128,"rawp":0.029,"real":45,"realp":0.022},{"name":"Decidueye","usage":0.01046,"raw":198,"rawp":0.045,"real":71,"realp":0.035},{"name":"Coalossal","usage":0.01021,"raw":178,"rawp":0.041,"real":68,"realp":0.033},{"name":"Oricorio-Pom-Pom","usage":0.00996,"raw":218,"rawp":0.05,"real":79,"realp":0.039},{"name":"Eelektross","usage":0.0097,"raw":140,"rawp":0.032,"real":77,"realp":0.038},{"name":"Cramorant","usage":0.00955,"raw":148,"rawp":0.034,"real":58,"realp":0.028},{"name":"Falinks","usage":0.00949,"raw":133,"rawp":0.03,"real":48,"realp":0.023},{"name":"Stantler","usage":0.00927,"raw":89,"rawp":0.02,"real":44,"realp":0.022},{"name":"Leafeon","usage":0.00903,"raw":157,"rawp":0.036,"real":61,"realp":0.03},{"name":"Lycanroc-Dusk","usage":0.0084,"raw":174,"rawp":0.04,"real":61,"realp":0.03},{"name":"Heracross","usage":0.00837,"raw":106,"rawp":0.024,"real":51,"realp":0.025},{"name":"Clawitzer","usage":0.00828,"raw":177,"rawp":0.04,"real":69,"realp":0.034},{"name":"Typhlosion","usage":0.00813,"raw":170,"rawp":0.039,"real":81,"realp":0.04},{"name":"Furret","usage":0.00803,"raw":83,"rawp":0.019,"real":34,"realp":0.017},{"name":"Froslass","usage":0.00782,"raw":171,"rawp":0.039,"real":71,"realp":0.035},{"name":"Raichu-Alola","usage":0.0078,"raw":146,"rawp":0.033,"real":55,"realp":0.027},{"name":"Carbink","usage":0.0077,"raw":80,"rawp":0.018,"real":30,"realp":0.015},{"name":"Ampharos","usage":0.00766,"raw":135,"rawp":0.031,"real":60,"realp":0.029},{"name":"Camerupt","usage":0.00765,"raw":86,"rawp":0.02,"real":30,"realp":0.015},{"name":"Lokix","usage":0.00742,"raw":92,"rawp":0.021,"real":39,"realp":0.019},{"name":"Leavanny","usage":0.00734,"raw":86,"rawp":0.02,"real":23,"realp":0.011},{"name":"Lumineon","usage":0.007,"raw":68,"rawp":0.015,"real":28,"realp":0.014},{"name":"Beartic","usage":0.00687,"raw":157,"rawp":0.036,"real":72,"realp":0.035},{"name":"Blissey","usage":0.00687,"raw":148,"rawp":0.034,"real":56,"realp":0.027},{"name":"Quagsire","usage":0.00661,"raw":98,"rawp":0.022,"real":30,"realp":0.015},{"name":"Masquerain","usage":0.00651,"raw":140,"rawp":0.032,"real":49,"realp":0.024},{"name":"Ariados","usage":0.00632,"raw":72,"rawp":0.016,"real":26,"realp":0.013},{"name":"Sunflora","usage":0.00621,"raw":28,"rawp":0.006,"real":5,"realp":0.002},{"name":"Dedenne","usage":0.00618,"raw":42,"rawp":0.01,"real":18,"realp":0.009},{"name":"Dusknoir","usage":0.0059,"raw":76,"rawp":0.017,"real":25,"realp":0.012},{"name":"Graveler-Alola","usage":0.00554,"raw":19,"rawp":0.004,"real":7,"realp":0.003},{"name":"Phanpy","usage":0.00551,"raw":44,"rawp":0.01,"real":32,"realp":0.016},{"name":"Crabominable","usage":0.00548,"raw":117,"rawp":0.027,"real":54,"realp":0.026},{"name":"Scyther","usage":0.00543,"raw":94,"rawp":0.021,"real":31,"realp":0.015},{"name":"Palossand","usage":0.00541,"raw":101,"rawp":0.023,"real":45,"realp":0.022},{"name":"Gogoat","usage":0.00537,"raw":83,"rawp":0.019,"real":32,"realp":0.016},{"name":"Flapple","usage":0.00509,"raw":62,"rawp":0.014,"real":18,"realp":0.009},{"name":"Slowpoke","usage":0.00503,"raw":129,"rawp":0.029,"real":53,"realp":0.026},{"name":"Copperajah","usage":0.00501,"raw":111,"rawp":0.025,"real":38,"realp":0.019},{"name":"Monferno","usage":0.00499,"raw":18,"rawp":0.004,"real":2,"realp":0.001},{"name":"Shellos","usage":0.00493,"raw":22,"rawp":0.005,"real":13,"realp":0.006},{"name":"Eevee","usage":0.00491,"raw":22,"rawp":0.005,"real":6,"realp":0.003},{"name":"Honchkrow","usage":0.00461,"raw":62,"rawp":0.014,"real":28,"realp":0.014},{"name":"Zoroark","usage":0.00442,"raw":47,"rawp":0.011,"real":7,"realp":0.003},{"name":"Rotom-Frost","usage":0.00441,"raw":88,"rawp":0.02,"real":47,"realp":0.023},{"name":"Golem","usage":0.00441,"raw":54,"rawp":0.012,"real":32,"realp":0.016},{"name":"Flareon","usage":0.00428,"raw":53,"rawp":0.012,"real":32,"realp":0.016},{"name":"Oricorio","usage":0.00404,"raw":63,"rawp":0.014,"real":28,"realp":0.014},{"name":"Lycanroc-Midnight","usage":0.00402,"raw":62,"rawp":0.014,"real":28,"realp":0.014},{"name":"Ursaring","usage":0.00396,"raw":38,"rawp":0.009,"real":14,"realp":0.007},{"name":"Sandslash","usage":0.00394,"raw":87,"rawp":0.02,"real":50,"realp":0.024},{"name":"Greedent","usage":0.00391,"raw":80,"rawp":0.018,"real":33,"realp":0.016},{"name":"Bombirdier","usage":0.00387,"raw":27,"rawp":0.006,"real":11,"realp":0.005},{"name":"Morpeko","usage":0.00383,"raw":76,"rawp":0.017,"real":38,"realp":0.019},{"name":"Foongus","usage":0.00383,"raw":21,"rawp":0.005,"real":9,"realp":0.004},{"name":"Pyroar","usage":0.00373,"raw":18,"rawp":0.004,"real":6,"realp":0.003},{"name":"Polteageist","usage":0.00369,"raw":105,"rawp":0.024,"real":27,"realp":0.013},{"name":"Mismagius","usage":0.00366,"raw":68,"rawp":0.015,"real":27,"realp":0.013},{"name":"Sandaconda","usage":0.00351,"raw":57,"rawp":0.013,"real":33,"realp":0.016},{"name":"Probopass","usage":0.00345,"raw":51,"rawp":0.012,"real":20,"realp":0.01},{"name":"Jigglypuff","usage":0.00338,"raw":21,"rawp":0.005,"real":6,"realp":0.003},{"name":"Spidops","usage":0.00325,"raw":65,"rawp":0.015,"real":12,"realp":0.006},{"name":"Houndoom","usage":0.00315,"raw":39,"rawp":0.009,"real":22,"realp":0.011},{"name":"Delibird","usage":0.00301,"raw":39,"rawp":0.009,"real":7,"realp":0.003},{"name":"Chimecho","usage":0.00296,"raw":38,"rawp":0.009,"real":8,"realp":0.004},{"name":"Wigglytuff","usage":0.00295,"raw":60,"rawp":0.014,"real":27,"realp":0.013},{"name":"Venomoth","usage":0.00284,"raw":25,"rawp":0.006,"real":7,"realp":0.003},{"name":"Mabosstiff","usage":0.00279,"raw":32,"rawp":0.007,"real":14,"realp":0.007},{"name":"Koffing","usage":0.00277,"raw":41,"rawp":0.009,"real":13,"realp":0.006},{"name":"Sneasel","usage":0.00275,"raw":21,"rawp":0.005,"real":6,"realp":0.003},{"name":"Passimian","usage":0.0027,"raw":27,"rawp":0.006,"real":15,"realp":0.007},{"name":"Cacturne","usage":0.00263,"raw":46,"rawp":0.01,"real":16,"realp":0.008},{"name":"Dugtrio","usage":0.00261,"raw":64,"rawp":0.015,"real":37,"realp":0.018},{"name":"Tauros","usage":0.00254,"raw":32,"rawp":0.007,"real":12,"realp":0.006},{"name":"Squawkabilly","usage":0.0025,"raw":75,"rawp":0.017,"real":34,"realp":0.017},{"name":"Wugtrio","usage":0.00219,"raw":28,"rawp":0.006,"real":9,"realp":0.004},{"name":"Nosepass","usage":0.00207,"raw":6,"rawp":0.001,"real":0,"realp":0},{"name":"Thwackey","usage":0.00204,"raw":13,"rawp":0.003,"real":3,"realp":0.001},{"name":"Noctowl","usage":0.00202,"raw":30,"rawp":0.007,"real":10,"realp":0.005},{"name":"Dunsparce","usage":0.00201,"raw":44,"rawp":0.01,"real":21,"realp":0.01},{"name":"Grumpig","usage":0.00199,"raw":30,"rawp":0.007,"real":11,"realp":0.005},{"name":"Riolu","usage":0.00197,"raw":49,"rawp":0.011,"real":9,"realp":0.004},{"name":"Tropius","usage":0.00187,"raw":41,"rawp":0.009,"real":18,"realp":0.009},{"name":"Vespiquen","usage":0.00182,"raw":16,"rawp":0.004,"real":3,"realp":0.001},{"name":"Whiscash","usage":0.00177,"raw":9,"rawp":0.002,"real":3,"realp":0.001},{"name":"Hypno","usage":0.00175,"raw":30,"rawp":0.007,"real":7,"realp":0.003},{"name":"Piloswine","usage":0.00174,"raw":14,"rawp":0.003,"real":7,"realp":0.003},{"name":"Gligar","usage":0.00168,"raw":10,"rawp":0.002,"real":2,"realp":0.001},{"name":"Prinplup","usage":0.00163,"raw":8,"rawp":0.002,"real":1,"realp":0},{"name":"Sawsbuck","usage":0.00154,"raw":33,"rawp":0.008,"real":16,"realp":0.008},{"name":"Dugtrio-Alola","usage":0.00148,"raw":27,"rawp":0.006,"real":17,"realp":0.008},{"name":"Rotom-Fan","usage":0.0014,"raw":8,"rawp":0.002,"real":2,"realp":0.001},{"name":"Bronzor","usage":0.00138,"raw":4,"rawp":0.001,"real":0,"realp":0},{"name":"Greavard","usage":0.00136,"raw":6,"rawp":0.001,"real":0,"realp":0},{"name":"Primeape","usage":0.00132,"raw":62,"rawp":0.014,"real":26,"realp":0.013},{"name":"Oinkologne-F","usage":0.00132,"raw":73,"rawp":0.017,"real":30,"realp":0.015},{"name":"Magneton","usage":0.00131,"raw":23,"rawp":0.005,"real":10,"realp":0.005},{"name":"Duskull","usage":0.00129,"raw":8,"rawp":0.002,"real":2,"realp":0.001},{"name":"Persian","usage":0.00128,"raw":19,"rawp":0.004,"real":10,"realp":0.005},{"name":"Muk","usage":0.00123,"raw":31,"rawp":0.007,"real":9,"realp":0.004},{"name":"Swalot","usage":0.00122,"raw":97,"rawp":0.022,"real":25,"realp":0.012},{"name":"Sudowoodo","usage":0.00118,"raw":39,"rawp":0.009,"real":16,"realp":0.008},{"name":"Cleffa","usage":0.00118,"raw":11,"rawp":0.003,"real":5,"realp":0.002},{"name":"Quaxly","usage":0.00114,"raw":5,"rawp":0.001,"real":0,"realp":0},{"name":"Mesprit","usage":0.00111,"raw":27,"rawp":0.006,"real":10,"realp":0.005},{"name":"Glalie","usage":0.00106,"raw":20,"rawp":0.005,"real":6,"realp":0.003},{"name":"Spinarak","usage":0.00103,"raw":3,"rawp":0.001,"real":1,"realp":0},{"name":"Veluza","usage":0.00098,"raw":10,"rawp":0.002,"real":2,"realp":0.001},{"name":"Electrode","usage":0.00096,"raw":19,"rawp":0.004,"real":7,"realp":0.003},{"name":"Donphan","usage":0.00096,"raw":7,"rawp":0.002,"real":2,"realp":0.001},{"name":"Zangoose","usage":0.00095,"raw":22,"rawp":0.005,"real":8,"realp":0.004},{"name":"Psyduck","usage":0.00095,"raw":10,"rawp":0.002,"real":3,"realp":0.001},{"name":"Mightyena","usage":0.00091,"raw":8,"rawp":0.002,"real":4,"realp":0.002},{"name":"Klawf","usage":0.00088,"raw":17,"rawp":0.004,"real":7,"realp":0.003},{"name":"Sliggoo-Hisui","usage":0.00081,"raw":14,"rawp":0.003,"real":5,"realp":0.002},{"name":"Samurott","usage":0.00077,"raw":29,"rawp":0.007,"real":12,"realp":0.006},{"name":"Toedscool","usage":0.00077,"raw":18,"rawp":0.004,"real":4,"realp":0.002},{"name":"Hoothoot","usage":0.00073,"raw":7,"rawp":0.002,"real":6,"realp":0.003},{"name":"Gurdurr","usage":0.0007,"raw":8,"rawp":0.002,"real":5,"realp":0.002},{"name":"Sneasel-Hisui","usage":0.00059,"raw":4,"rawp":0.001,"real":2,"realp":0.001},{"name":"Slowpoke-Galar","usage":0.00058,"raw":9,"rawp":0.002,"real":1,"realp":0},{"name":"Skuntank","usage":0.00052,"raw":23,"rawp":0.005,"real":12,"realp":0.006},{"name":"Vulpix-Alola","usage":0.00052,"raw":4,"rawp":0.001,"real":3,"realp":0.001},{"name":"Dartrix","usage":0.00051,"raw":2,"rawp":0,"real":0,"realp":0},{"name":"Banette","usage":0.00048,"raw":4,"rawp":0.001,"real":2,"realp":0.001},{"name":"Vigoroth","usage":0.00048,"raw":8,"rawp":0.002,"real":1,"realp":0},{"name":"Qwilfish","usage":0.00047,"raw":31,"rawp":0.007,"real":13,"realp":0.006},{"name":"Oinkologne","usage":0.00044,"raw":11,"rawp":0.003,"real":5,"realp":0.002},{"name":"Basculin","usage":0.00041,"raw":9,"rawp":0.002,"real":3,"realp":0.001},{"name":"Lechonk","usage":0.00041,"raw":4,"rawp":0.001,"real":1,"realp":0},{"name":"Oricorio-Pa'u","usage":0.00038,"raw":5,"rawp":0.001,"real":2,"realp":0.001},{"name":"Naclstack","usage":0.00038,"raw":9,"rawp":0.002,"real":1,"realp":0},{"name":"Tandemaus","usage":0.00037,"raw":5,"rawp":0.001,"real":4,"realp":0.002},{"name":"Girafarig","usage":0.00036,"raw":19,"rawp":0.004,"real":9,"realp":0.004},{"name":"Crocalor","usage":0.00035,"raw":10,"rawp":0.002,"real":2,"realp":0.001},{"name":"Grotle","usage":0.00035,"raw":2,"rawp":0,"real":1,"realp":0},{"name":"Teddiursa","usage":0.00035,"raw":1,"rawp":0,"real":0,"realp":0},{"name":"Scatterbug","usage":0.00035,"raw":1,"rawp":0,"real":0,"realp":0},{"name":"Numel","usage":0.00034,"raw":2,"rawp":0,"real":2,"realp":0.001},{"name":"Hattrem","usage":0.00034,"raw":7,"rawp":0.002,"real":3,"realp":0.001},{"name":"Gumshoos","usage":0.00033,"raw":8,"rawp":0.002,"real":5,"realp":0.002},{"name":"Poltchageist","usage":0.00029,"raw":2,"rawp":0,"real":1,"realp":0},{"name":"Tauros-Paldea-Combat","usage":0.00029,"raw":13,"rawp":0.003,"real":8,"realp":0.004},{"name":"Fuecoco","usage":0.00028,"raw":1,"rawp":0,"real":0,"realp":0},{"name":"Magikarp","usage":0.00028,"raw":8,"rawp":0.002,"real":3,"realp":0.001},{"name":"Croagunk","usage":0.00028,"raw":4,"rawp":0.001,"real":1,"realp":0},{"name":"Fletchinder","usage":0.00027,"raw":1,"rawp":0,"real":0,"realp":0},{"name":"Swanna","usage":0.00024,"raw":3,"rawp":0.001,"real":2,"realp":0.001},{"name":"Zorua","usage":0.00022,"raw":3,"rawp":0.001,"real":1,"realp":0},{"name":"Haunter","usage":0.00022,"raw":26,"rawp":0.006,"real":14,"realp":0.007},{"name":"Skrelp","usage":0.00022,"raw":1,"rawp":0,"real":0,"realp":0},{"name":"Quilava","usage":0.00022,"raw":1,"rawp":0,"real":1,"realp":0},{"name":"Floragato","usage":0.00019,"raw":5,"rawp":0.001,"real":2,"realp":0.001},{"name":"Feebas","usage":0.00019,"raw":2,"rawp":0,"real":0,"realp":0},{"name":"Slugma","usage":0.00019,"raw":2,"rawp":0,"real":0,"realp":0},{"name":"Komala","usage":0.00018,"raw":10,"rawp":0.002,"real":5,"realp":0.002},{"name":"Nacli","usage":0.00018,"raw":4,"rawp":0.001,"real":0,"realp":0},{"name":"Venonat","usage":0.00017,"raw":7,"rawp":0.002,"real":2,"realp":0.001},{"name":"Igglybuff","usage":0.00017,"raw":1,"rawp":0,"real":0,"realp":0},{"name":"Eelektrik","usage":0.00016,"raw":2,"rawp":0,"real":2,"realp":0.001},{"name":"Zweilous","usage":0.00016,"raw":5,"rawp":0.001,"real":3,"realp":0.001},{"name":"Charcadet","usage":0.00015,"raw":2,"rawp":0,"real":0,"realp":0},{"name":"Drowzee","usage":0.00013,"raw":23,"rawp":0.005,"real":5,"realp":0.002},{"name":"Maschiff","usage":0.00013,"raw":1,"rawp":0,"real":0,"realp":0},{"name":"Drakloak","usage":0.00013,"raw":1,"rawp":0,"real":0,"realp":0},{"name":"Pawmo","usage":0.00013,"raw":1,"rawp":0,"real":0,"realp":0},{"name":"Weepinbell","usage":0.00012,"raw":1,"rawp":0,"real":1,"realp":0},{"name":"Nymble","usage":0.00012,"raw":1,"rawp":0,"real":0,"realp":0},{"name":"Fidough","usage":0.00012,"raw":1,"rawp":0,"real":0,"realp":0},{"name":"Munchlax","usage":0.00011,"raw":7,"rawp":0.002,"real":2,"realp":0.001},{"name":"Diglett","usage":0.00011,"raw":1,"rawp":0,"real":1,"realp":0},{"name":"Azurill","usage":0.00011,"raw":3,"rawp":0.001,"real":1,"realp":0},{"name":"Happiny","usage":0.0001,"raw":1,"rawp":0,"real":0,"realp":0},{"name":"Kricketune","usage":0.0001,"raw":2,"rawp":0,"real":0,"realp":0},{"name":"Braixen","usage":0.00008,"raw":6,"rawp":0.001,"real":2,"realp":0.001},{"name":"Poliwhirl","usage":0.00007,"raw":7,"rawp":0.002,"real":0,"realp":0},{"name":"Swadloon","usage":0.00006,"raw":2,"rawp":0,"real":2,"realp":0.001},{"name":"Graveler","usage":0.00006,"raw":15,"rawp":0.003,"real":12,"realp":0.006},{"name":"Frigibax","usage":0.00006,"raw":1,"rawp":0,"real":0,"realp":0},{"name":"Wingull","usage":0.00006,"raw":1,"rawp":0,"real":0,"realp":0},{"name":"Seviper","usage":0.00005,"raw":5,"rawp":0.001,"real":3,"realp":0.001},{"name":"Pichu","usage":0.00004,"raw":1,"rawp":0,"real":1,"realp":0},{"name":"Aipom","usage":0.00003,"raw":3,"rawp":0.001,"real":2,"realp":0.001},{"name":"Glimmet","usage":0.00002,"raw":1,"rawp":0,"real":1,"realp":0},{"name":"Lampent","usage":0.00002,"raw":2,"rawp":0,"real":1,"realp":0},{"name":"Luvdisc","usage":0.00001,"raw":1,"rawp":0,"real":0,"realp":0},{"name":"Gastly","usage":0.00001,"raw":6,"rawp":0.001,"real":2,"realp":0.001},{"name":"Gimmighoul","usage":0.00001,"raw":1,"rawp":0,"real":1,"realp":0},{"name":"Mudbray","usage":0.00001,"raw":1,"rawp":0,"real":1,"realp":0},{"name":"Meditite","usage":0.00001,"raw":11,"rawp":0.003,"real":7,"realp":0.003},{"name":"Shroomish","usage":0,"raw":13,"rawp":0.003,"real":4,"realp":0.002},{"name":"Gothita","usage":0,"raw":1,"rawp":0,"real":0,"realp":0},{"name":"Rotom","usage":0,"raw":6,"rawp":0.001,"real":4,"realp":0.002},{"name":"Gabite","usage":0,"raw":14,"rawp":0.003,"real":8,"realp":0.004},{"name":"Pupitar","usage":0,"raw":5,"rawp":0.001,"real":3,"realp":0.001},{"name":"Fraxure","usage":0,"raw":1,"rawp":0,"real":1,"realp":0},{"name":"Piplup","usage":0,"raw":6,"rawp":0.001,"real":1,"realp":0},{"name":"Gulpin","usage":0,"raw":8,"rawp":0.002,"real":1,"realp":0},{"name":"Axew","usage":0,"raw":1,"rawp":0,"real":0,"realp":0},{"name":"Chingling","usage":0,"raw":2,"rawp":0,"real":0,"realp":0},{"name":"Flaaffy","usage":0,"raw":5,"rawp":0.001,"real":4,"realp":0.002},{"name":"Mankey","usage":0,"raw":1,"rawp":0,"real":0,"realp":0},{"name":"Morgrem","usage":0,"raw":2,"rawp":0,"real":2,"realp":0.001},{"name":"Meowth","usage":0,"raw":2,"rawp":0,"real":0,"realp":0},{"name":"Dragonair","usage":0,"raw":2,"rawp":0,"real":1,"realp":0}]}