{"screamtail":{"usage":50,"raw":33,"avg":1,"vc":70,"abilities":[{"name":"Magic Bounce","usage":100}],"moves":[{"name":"Teleport","usage":78.788},{"name":"Wish","usage":48.485},{"name":"Reflect","usage":39.394},{"name":"Light Screen","usage":39.394},{"name":"Protect","usage":27.273},{"name":"Stored Power","usage":21.212},{"name":"Bulk Up","usage":21.212},{"name":"Calm Mind","usage":21.212},{"name":"Draining Kiss","usage":21.212},{"name":"Healing Wish","usage":18.182},{"name":"Psychic","usage":15.152},{"name":"Nuzzle","usage":12.121},{"name":"Trick Room","usage":12.121},{"name":"Encore","usage":12.121},{"name":"Other","usage":12.121}],"items":[{"name":"Leftovers","usage":78.788},{"name":"Covert Cloak","usage":21.212}],"spreads":[{"nature":"Timid","evs":{"hp":36,"atk":0,"def":108,"spa":0,"spd":112,"spe":252},"usage":39.394},{"nature":"Bold","evs":{"hp":252,"atk":0,"def":252,"spa":0,"spd":4,"spe":0},"usage":36.364},{"nature":"Jolly","evs":{"hp":252,"atk":4,"def":0,"spa":0,"spd":0,"spe":252},"usage":12.121},{"nature":"Sassy","evs":{"hp":252,"atk":0,"def":4,"spa":0,"spd":252,"spe":0},"usage":9.091},{"nature":"Other","evs":{"hp":null,"atk":null,"def":null,"spa":null,"spd":null,"spe":null},"usage":3.03}],"teammates":[{"name":"Forretress","usage":60.606},{"name":"Glastrier","usage":45.455},{"name":"Chandelure","usage":39.394},{"name":"Conkeldurr","usage":39.394},{"name":"Slowking-Galar","usage":39.394},{"name":"Barraskewda","usage":24.242},{"name":"Landorus-Therian","usage":24.242},{"name":"Vaporeon","usage":21.212},{"name":"Jolteon","usage":21.212},{"name":"Zarude","usage":21.212},{"name":"Fezandipiti","usage":15.152}],"counters":[],"lead":{"usage":22.72727,"raw":15,"rawp":22.727}},"forretress":{"usage":30.30303,"raw":20,"avg":1,"vc":70,"abilities":[{"name":"Technician","usage":65},{"name":"Sturdy","usage":35}],"moves":[{"name":"U-turn","usage":65},{"name":"Reflect","usage":65},{"name":"Bullet Punch","usage":60},{"name":"Pin Missile","usage":35},{"name":"Stealth Rock","usage":35},{"name":"Spikes","usage":35},{"name":"Rapid Spin","usage":35},{"name":"Tailwind","usage":30},{"name":"Knock Off","usage":15},{"name":"Swords Dance","usage":10},{"name":"Other","usage":15}],"items":[{"name":"Leftovers","usage":45},{"name":"Heavy-Duty Boots","usage":35},{"name":"Life Orb","usage":20}],"spreads":[{"nature":"Brave","evs":{"hp":4,"atk":252,"def":252,"spa":0,"spd":0,"spe":0},"usage":40},{"nature":"Impish","evs":{"hp":252,"atk":4,"def":252,"spa":0,"spd":0,"spe":0},"usage":35},{"nature":"Adamant","evs":{"hp":4,"atk":252,"def":252,"spa":0,"spd":0,"spe":0},"usage":10},{"nature":"Relaxed","evs":{"hp":252,"atk":4,"def":252,"spa":0,"spd":0,"spe":0},"usage":10},{"nature":"Relaxed","evs":{"hp":4,"atk":252,"def":252,"spa":0,"spd":0,"spe":0},"usage":5}],"teammates":[{"name":"Scream Tail","usage":100},{"name":"Slowking-Galar","usage":65},{"name":"Conkeldurr","usage":65},{"name":"Chandelure","usage":65},{"name":"Glastrier","usage":60},{"name":"Barraskewda","usage":40},{"name":"Vaporeon","usage":35},{"name":"Jolteon","usage":35},{"name":"Zarude","usage":35}],"counters":[],"lead":{"usage":4.54545,"raw":3,"rawp":4.545}},"chandelure":{"usage":25.75758,"raw":17,"avg":1,"vc":70,"abilities":[{"name":"Weak Armor","usage":88.235},{"name":"Infiltrator","usage":11.765}],"moves":[{"name":"Torch Song","usage":88.235},{"name":"Acid Armor","usage":76.471},{"name":"Energy Ball","usage":76.471},{"name":"Stored Power","usage":76.471},{"name":"Calm Mind","usage":23.529},{"name":"Eruption","usage":23.529},{"name":"Shadow Ball","usage":23.529},{"name":"Other","usage":11.765}],"items":[{"name":"Weakness Policy","usage":76.471},{"name":"Choice Scarf","usage":11.765},{"name":"Choice Specs","usage":11.765}],"spreads":[{"nature":"Modest","evs":{"hp":4,"atk":0,"def":100,"spa":152,"spd":0,"spe":252},"usage":41.176},{"nature":"Modest","evs":{"hp":4,"atk":0,"def":252,"spa":0,"spd":0,"spe":252},"usage":29.412},{"nature":"Timid","evs":{"hp":0,"atk":0,"def":0,"spa":252,"spd":4,"spe":252},"usage":23.529},{"nature":"Modest","evs":{"hp":4,"atk":0,"def":80,"spa":252,"spd":100,"spe":72},"usage":5.882}],"teammates":[{"name":"Slowking-Galar","usage":76.471},{"name":"Conkeldurr","usage":76.471},{"name":"Forretress","usage":76.471},{"name":"Scream Tail","usage":76.471},{"name":"Glastrier","usage":70.588},{"name":"Milotic","usage":23.529},{"name":"Fezandipiti","usage":11.765},{"name":"Zarude","usage":11.765},{"name":"Samurott-Hisui","usage":11.765},{"name":"Landorus-Therian","usage":11.765},{"name":"Hippowdon","usage":11.765}],"counters":[],"lead":{"usage":1.51515,"raw":1,"rawp":1.515}},"landorustherian":{"usage":24.24242,"raw":16,"avg":1,"vc":83,"abilities":[{"name":"Poison Heal","usage":100}],"moves":[{"name":"Earthquake","usage":100},{"name":"U-turn","usage":75},{"name":"Stealth Rock","usage":50},{"name":"Protect","usage":37.5},{"name":"Knock Off","usage":31.25},{"name":"Facade","usage":31.25},{"name":"Toxic Spikes","usage":18.75},{"name":"Toxic","usage":12.5},{"name":"Stone Edge","usage":12.5},{"name":"Swords Dance","usage":12.5},{"name":"Other","usage":18.75}],"items":[{"name":"Toxic Orb","usage":100}],"spreads":[{"nature":"Jolly","evs":{"hp":0,"atk":252,"def":0,"spa":0,"spd":4,"spe":252},"usage":31.25},{"nature":"Adamant","evs":{"hp":252,"atk":252,"def":4,"spa":0,"spd":0,"spe":0},"usage":31.25},{"nature":"Hardy","evs":{"hp":252,"atk":0,"def":200,"spa":0,"spd":56,"spe":0},"usage":18.75},{"nature":"Impish","evs":{"hp":252,"atk":4,"def":252,"spa":0,"spd":0,"spe":0},"usage":12.5},{"nature":"Careful","evs":{"hp":252,"atk":56,"def":0,"spa":0,"spd":196,"spe":4},"usage":6.25}],"teammates":[{"name":"Milotic","usage":62.5},{"name":"Scream Tail","usage":50},{"name":"Fezandipiti","usage":37.5},{"name":"Shaymin","usage":31.25},{"name":"Dusknoir","usage":31.25},{"name":"Chesnaught","usage":31.25},{"name":"Samurott-Hisui","usage":31.25},{"name":"Flareon","usage":18.75},{"name":"Haxorus","usage":18.75},{"name":"Articuno-Galar","usage":18.75},{"name":"Gengar","usage":18.75}],"counters":[],"lead":{"usage":7.57576,"raw":5,"rawp":7.576}},"glastrier":{"usage":24.24242,"raw":16,"avg":1,"vc":70,"abilities":[{"name":"Snow Warning","usage":81.25},{"name":"Chilling Neigh","usage":18.75}],"moves":[{"name":"Ice Shard","usage":93.75},{"name":"Earthquake","usage":93.75},{"name":"Aurora Veil","usage":81.25},{"name":"Belly Drum","usage":75},{"name":"Ice Spinner","usage":18.75},{"name":"Heavy Slam","usage":18.75},{"name":"Other","usage":18.75}],"items":[{"name":"Heavy-Duty Boots","usage":81.25},{"name":"Life Orb","usage":18.75}],"spreads":[{"nature":"Adamant","evs":{"hp":4,"atk":252,"def":252,"spa":0,"spd":0,"spe":0},"usage":50},{"nature":"Brave","evs":{"hp":4,"atk":252,"def":252,"spa":0,"spd":0,"spe":0},"usage":25},{"nature":"Brave","evs":{"hp":248,"atk":252,"def":0,"spa":0,"spd":8,"spe":0},"usage":18.75},{"nature":"Adamant","evs":{"hp":248,"atk":252,"def":0,"spa":0,"spd":8,"spe":0},"usage":6.25}],"teammates":[{"name":"Scream Tail","usage":93.75},{"name":"Slowking-Galar","usage":75},{"name":"Conkeldurr","usage":75},{"name":"Forretress","usage":75},{"name":"Chandelure","usage":75},{"name":"Clawitzer","usage":18.75},{"name":"Ursaluna","usage":18.75},{"name":"Brute Bonnet","usage":18.75},{"name":"Ceruledge","usage":18.75},{"name":"Breloom","usage":6.25},{"name":"Okidogi","usage":6.25}],"counters":[],"lead":{"usage":3.0303,"raw":2,"rawp":3.03}},"conkeldurr":{"usage":21.21212,"raw":14,"avg":1,"vc":70,"abilities":[{"name":"Regenerator","usage":92.857},{"name":"Guts","usage":7.143}],"moves":[{"name":"Close Combat","usage":92.857},{"name":"Earthquake","usage":92.857},{"name":"Mach Punch","usage":78.571},{"name":"Gunk Shot","usage":57.143},{"name":"Knock Off","usage":42.857},{"name":"Ice Punch","usage":14.286},{"name":"Headlong Rush","usage":7.143},{"name":"Other","usage":14.286}],"items":[{"name":"Life Orb","usage":92.857},{"name":"Flame Orb","usage":7.143}],"spreads":[{"nature":"Brave","evs":{"hp":4,"atk":252,"def":252,"spa":0,"spd":0,"spe":0},"usage":57.143},{"nature":"Adamant","evs":{"hp":4,"atk":252,"def":252,"spa":0,"spd":0,"spe":0},"usage":35.714},{"nature":"Adamant","evs":{"hp":0,"atk":252,"def":48,"spa":0,"spd":208,"spe":0},"usage":7.143}],"teammates":[{"name":"Slowking-Galar","usage":92.857},{"name":"Chandelure","usage":92.857},{"name":"Forretress","usage":92.857},{"name":"Scream Tail","usage":92.857},{"name":"Glastrier","usage":85.714},{"name":"Milotic","usage":7.143},{"name":"Scizor","usage":7.143},{"name":"Oricorio-Sensu","usage":7.143},{"name":"Oricorio-Sensu","usage":7.143}],"counters":[],"lead":{"usage":0,"raw":0,"rawp":0}},"gengar":{"usage":19.69697,"raw":13,"avg":1,"vc":59,"abilities":[{"name":"Levitate","usage":84.615},{"name":"Cursed Body","usage":15.385}],"moves":[{"name":"Nasty Plot","usage":100},{"name":"Shadow Ball","usage":76.923},{"name":"Psychic","usage":46.154},{"name":"Gunk Shot","usage":46.154},{"name":"Sludge Bomb","usage":30.769},{"name":"Dazzling Gleam","usage":30.769},{"name":"Venoshock","usage":23.077},{"name":"Thunderbolt","usage":23.077},{"name":"Hex","usage":23.077}],"items":[{"name":"Focus Sash","usage":61.538},{"name":"Black Sludge","usage":23.077},{"name":"Wise Glasses","usage":15.385}],"spreads":[{"nature":"Timid","evs":{"hp":0,"atk":0,"def":0,"spa":252,"spd":4,"spe":252},"usage":53.846},{"nature":"Modest","evs":{"hp":0,"atk":4,"def":0,"spa":252,"spd":0,"spe":252},"usage":46.154}],"teammates":[{"name":"Cinderace","usage":61.538},{"name":"Scyther","usage":53.846},{"name":"Gyarados","usage":46.154},{"name":"Corviknight","usage":46.154},{"name":"Fezandipiti","usage":30.769},{"name":"Iron Treads","usage":30.769},{"name":"Ogerpon","usage":30.769},{"name":"Zarude","usage":30.769},{"name":"Dusclops","usage":23.077},{"name":"Milotic","usage":23.077},{"name":"Flareon","usage":23.077}],"counters":[],"lead":{"usage":1.51515,"raw":1,"rawp":1.515}},"milotic":{"usage":19.69697,"raw":13,"avg":1,"vc":64,"abilities":[{"name":"Regenerator","usage":100}],"moves":[{"name":"Flip Turn","usage":92.308},{"name":"Scald","usage":84.615},{"name":"Rapid Spin","usage":61.538},{"name":"Dragon Tail","usage":38.462},{"name":"Knock Off","usage":23.077},{"name":"Wish","usage":23.077},{"name":"Ice Beam","usage":23.077},{"name":"Chilling Water","usage":15.385},{"name":"Recover","usage":15.385},{"name":"Draining Kiss","usage":15.385},{"name":"Other","usage":7.692}],"items":[{"name":"Assault Vest","usage":61.538},{"name":"Leftovers","usage":38.462}],"spreads":[{"nature":"Sassy","evs":{"hp":252,"atk":0,"def":4,"spa":0,"spd":252,"spe":0},"usage":61.538},{"nature":"Bold","evs":{"hp":252,"atk":0,"def":252,"spa":0,"spd":4,"spe":0},"usage":15.385},{"nature":"Calm","evs":{"hp":252,"atk":0,"def":0,"spa":4,"spd":252,"spe":0},"usage":15.385},{"nature":"Bold","evs":{"hp":252,"atk":0,"def":208,"spa":48,"spd":0,"spe":0},"usage":7.692}],"teammates":[{"name":"Landorus-Therian","usage":76.923},{"name":"Fezandipiti","usage":53.846},{"name":"Chesnaught","usage":53.846},{"name":"Dusknoir","usage":38.462},{"name":"Scream Tail","usage":38.462},{"name":"Chandelure","usage":30.769},{"name":"Dusclops","usage":23.077},{"name":"Flareon","usage":23.077},{"name":"Scyther","usage":23.077},{"name":"Gengar","usage":23.077},{"name":"Hatterene","usage":15.385}],"counters":[],"lead":{"usage":6.06061,"raw":4,"rawp":6.061}},"zarude":{"usage":19.69697,"raw":13,"avg":1,"vc":54,"abilities":[{"name":"Wind Rider","usage":69.231},{"name":"Leaf Guard","usage":30.769}],"moves":[{"name":"Bulk Up","usage":84.615},{"name":"Power Trip","usage":53.846},{"name":"Amnesia","usage":53.846},{"name":"Trailblaze","usage":53.846},{"name":"Knock Off","usage":46.154},{"name":"Power Whip","usage":30.769},{"name":"Jungle Healing","usage":30.769},{"name":"Tailwind","usage":15.385},{"name":"Flower Trick","usage":15.385},{"name":"Other","usage":15.385}],"items":[{"name":"Shell Bell","usage":53.846},{"name":"Leftovers","usage":30.769},{"name":"Life Orb","usage":15.385}],"spreads":[{"nature":"Jolly","evs":{"hp":0,"atk":252,"def":0,"spa":0,"spd":4,"spe":252},"usage":69.231},{"nature":"Adamant","evs":{"hp":252,"atk":252,"def":0,"spa":0,"spd":4,"spe":0},"usage":30.769}],"teammates":[{"name":"Vaporeon","usage":53.846},{"name":"Jolteon","usage":53.846},{"name":"Forretress","usage":53.846},{"name":"Scream Tail","usage":53.846},{"name":"Barraskewda","usage":53.846},{"name":"Cinderace","usage":30.769},{"name":"Gyarados","usage":30.769},{"name":"Gengar","usage":30.769},{"name":"Corviknight","usage":30.769},{"name":"Samurott-Hisui","usage":23.077},{"name":"Milotic","usage":15.385}],"counters":[],"lead":{"usage":3.0303,"raw":2,"rawp":3.03}},"slowkinggalar":{"usage":19.69697,"raw":13,"avg":1,"vc":70,"abilities":[{"name":"Regenerator","usage":100}],"moves":[{"name":"Parting Shot","usage":100},{"name":"Shell Side Arm","usage":92.308},{"name":"Trick Room","usage":84.615},{"name":"Toxic","usage":76.923},{"name":"Future Sight","usage":23.077},{"name":"Toxic Spikes","usage":15.385},{"name":"Other","usage":7.692}],"items":[{"name":"Heavy-Duty Boots","usage":92.308},{"name":"Life Orb","usage":7.692}],"spreads":[{"nature":"Sassy","evs":{"hp":252,"atk":0,"def":0,"spa":4,"spd":252,"spe":0},"usage":46.154},{"nature":"Sassy","evs":{"hp":252,"atk":0,"def":4,"spa":0,"spd":252,"spe":0},"usage":30.769},{"nature":"Quiet","evs":{"hp":4,"atk":0,"def":0,"spa":252,"spd":252,"spe":0},"usage":15.385},{"nature":"Sassy","evs":{"hp":252,"atk":0,"def":0,"spa":0,"spd":252,"spe":0},"usage":7.692}],"teammates":[{"name":"Forretress","usage":100},{"name":"Conkeldurr","usage":100},{"name":"Chandelure","usage":100},{"name":"Scream Tail","usage":100},{"name":"Glastrier","usage":92.308},{"name":"Glastrier","usage":92.308}],"counters":[],"lead":{"usage":1.51515,"raw":1,"rawp":1.515}},"fezandipiti":{"usage":18.18182,"raw":12,"avg":1,"vc":83,"abilities":[{"name":"Neutralizing Gas","usage":100}],"moves":[{"name":"Roost","usage":66.667},{"name":"Play Rough","usage":58.333},{"name":"Toxic","usage":50},{"name":"Taunt","usage":41.667},{"name":"Moonblast","usage":41.667},{"name":"Sludge Bomb","usage":33.333},{"name":"Calm Mind","usage":33.333},{"name":"Air Slash","usage":33.333},{"name":"U-turn","usage":16.667},{"name":"Will-O-Wisp","usage":16.667},{"name":"Other","usage":8.333}],"items":[{"name":"Black Sludge","usage":66.667},{"name":"Leftovers","usage":33.333}],"spreads":[{"nature":"Careful","evs":{"hp":252,"atk":4,"def":0,"spa":0,"spd":252,"spe":0},"usage":58.333},{"nature":"Timid","evs":{"hp":0,"atk":0,"def":0,"spa":252,"spd":4,"spe":252},"usage":33.333},{"nature":"Calm","evs":{"hp":252,"atk":0,"def":4,"spa":0,"spd":252,"spe":0},"usage":8.333}],"teammates":[{"name":"Chesnaught","usage":58.333},{"name":"Milotic","usage":58.333},{"name":"Landorus-Therian","usage":50},{"name":"Scream Tail","usage":41.667},{"name":"Dusknoir","usage":41.667},{"name":"Iron Treads","usage":33.333},{"name":"Ogerpon","usage":33.333},{"name":"Cinderace","usage":33.333},{"name":"Gengar","usage":33.333},{"name":"Scyther","usage":33.333},{"name":"Hatterene","usage":16.667}],"counters":[],"lead":{"usage":0,"raw":0,"rawp":0}},"jolteon":{"usage":16.66667,"raw":11,"avg":1,"vc":54,"abilities":[{"name":"Levitate","usage":100}],"moves":[{"name":"Cotton Guard","usage":63.636},{"name":"Calm Mind","usage":63.636},{"name":"Stored Power","usage":63.636},{"name":"Parabolic Charge","usage":63.636},{"name":"Thunderbolt","usage":36.364},{"name":"Volt Switch","usage":36.364},{"name":"Muddy Water","usage":36.364},{"name":"Flamethrower","usage":36.364}],"items":[{"name":"Covert Cloak","usage":63.636},{"name":"Choice Specs","usage":36.364}],"spreads":[{"nature":"Timid","evs":{"hp":0,"atk":0,"def":0,"spa":252,"spd":4,"spe":252},"usage":100}],"teammates":[{"name":"Barraskewda","usage":72.727},{"name":"Vaporeon","usage":63.636},{"name":"Forretress","usage":63.636},{"name":"Zarude","usage":63.636},{"name":"Scream Tail","usage":63.636},{"name":"Florges","usage":36.364},{"name":"Tauros-Paldea-Combat","usage":36.364},{"name":"Shaymin","usage":36.364},{"name":"Haxorus","usage":36.364},{"name":"Samurott","usage":27.273}],"counters":[],"lead":{"usage":4.54545,"raw":3,"rawp":4.545}},"shaymin":{"usage":15.15152,"raw":10,"avg":1,"vc":55,"abilities":[{"name":"Contrary","usage":100}],"moves":[{"name":"Leaf Storm","usage":100},{"name":"Earth Power","usage":80},{"name":"Synthesis","usage":60},{"name":"Giga Drain","usage":40},{"name":"Pollen Puff","usage":40},{"name":"Substitute","usage":30},{"name":"Psychic","usage":20},{"name":"Weather Ball","usage":20},{"name":"Other","usage":10}],"items":[{"name":"Leftovers","usage":90},{"name":"Life Orb","usage":10}],"spreads":[{"nature":"Timid","evs":{"hp":0,"atk":0,"def":0,"spa":252,"spd":4,"spe":252},"usage":100}],"teammates":[{"name":"Haxorus","usage":70},{"name":"Landorus-Therian","usage":50},{"name":"Tauros-Paldea-Combat","usage":40},{"name":"Jolteon","usage":40},{"name":"Florges","usage":40},{"name":"Samurott-Hisui","usage":30},{"name":"Articuno-Galar","usage":30},{"name":"Samurott","usage":30},{"name":"Scream Tail","usage":30},{"name":"Typhlosion","usage":20},{"name":"Slowbro","usage":20}],"counters":[],"lead":{"usage":1.51515,"raw":1,"rawp":1.515}},"haxorus":{"usage":13.63636,"raw":9,"avg":1,"vc":49,"abilities":[{"name":"Dragon's Maw","usage":55.556},{"name":"Sheer Force","usage":44.444}],"moves":[{"name":"First Impression","usage":55.556},{"name":"Iron Head","usage":55.556},{"name":"Rock Slide","usage":44.444},{"name":"Poison Jab","usage":44.444},{"name":"Dragon Rush","usage":44.444},{"name":"Fire Fang","usage":44.444},{"name":"Dragon Dance","usage":33.333},{"name":"Dragon Claw","usage":33.333},{"name":"Close Combat","usage":22.222},{"name":"Outrage","usage":22.222}],"items":[{"name":"Life Orb","usage":44.444},{"name":"Dragon Fang","usage":33.333},{"name":"Choice Band","usage":22.222}],"spreads":[{"nature":"Jolly","evs":{"hp":0,"atk":252,"def":0,"spa":0,"spd":4,"spe":252},"usage":66.667},{"nature":"Adamant","evs":{"hp":0,"atk":252,"def":0,"spa":0,"spd":4,"spe":252},"usage":33.333}],"teammates":[{"name":"Shaymin","usage":77.778},{"name":"Tauros-Paldea-Combat","usage":44.444},{"name":"Jolteon","usage":44.444},{"name":"Florges","usage":44.444},{"name":"Samurott-Hisui","usage":33.333},{"name":"Landorus-Therian","usage":33.333},{"name":"Articuno-Galar","usage":33.333},{"name":"Samurott","usage":33.333},{"name":"Scream Tail","usage":33.333},{"name":"Fezandipiti","usage":22.222},{"name":"Chesnaught","usage":22.222}],"counters":[],"lead":{"usage":3.0303,"raw":2,"rawp":3.03}},"barraskewda":{"usage":13.63636,"raw":9,"avg":1,"vc":70,"abilities":[{"name":"Rock Head","usage":88.889},{"name":"Adaptability","usage":11.111}],"moves":[{"name":"Brave Bird","usage":100},{"name":"Wave Crash","usage":88.889},{"name":"Head Smash","usage":77.778},{"name":"Coil","usage":77.778},{"name":"Flip Turn","usage":22.222},{"name":"Psychic Fangs","usage":11.111},{"name":"Aqua Jet","usage":11.111},{"name":"Other","usage":11.111}],"items":[{"name":"Shell Bell","usage":77.778},{"name":"Life Orb","usage":11.111},{"name":"Choice Band","usage":11.111}],"spreads":[{"nature":"Jolly","evs":{"hp":0,"atk":252,"def":0,"spa":0,"spd":4,"spe":252},"usage":88.889},{"nature":"Jolly","evs":{"hp":4,"atk":252,"def":0,"spa":0,"spd":0,"spe":252},"usage":11.111}],"teammates":[{"name":"Forretress","usage":88.889},{"name":"Jolteon","usage":88.889},{"name":"Scream Tail","usage":88.889},{"name":"Vaporeon","usage":77.778},{"name":"Zarude","usage":77.778},{"name":"Florges","usage":11.111},{"name":"Slowking-Galar","usage":11.111},{"name":"Conkeldurr","usage":11.111},{"name":"Tauros-Paldea-Combat","usage":11.111},{"name":"Chandelure","usage":11.111},{"name":"Chandelure","usage":11.111}],"counters":[],"lead":{"usage":3.0303,"raw":2,"rawp":3.03}},"cinderace":{"usage":13.63636,"raw":9,"avg":1,"vc":50,"abilities":[{"name":"Drought","usage":44.444},{"name":"Unaware","usage":44.444},{"name":"Magician","usage":11.111}],"moves":[{"name":"Pyro Ball","usage":100},{"name":"Sucker Punch","usage":88.889},{"name":"Dragon Dance","usage":88.889},{"name":"Earthquake","usage":44.444},{"name":"High Jump Kick","usage":44.444},{"name":"Taunt","usage":11.111},{"name":"Rapid Spin","usage":11.111},{"name":"Other","usage":11.111}],"items":[{"name":"Muscle Band","usage":44.444},{"name":"Heavy-Duty Boots","usage":44.444},{"name":"Focus Sash","usage":11.111}],"spreads":[{"nature":"Jolly","evs":{"hp":0,"atk":252,"def":0,"spa":0,"spd":4,"spe":252},"usage":55.556},{"nature":"Adamant","evs":{"hp":0,"atk":252,"def":0,"spa":0,"spd":4,"spe":252},"usage":44.444}],"teammates":[{"name":"Gengar","usage":88.889},{"name":"Fezandipiti","usage":44.444},{"name":"Iron Treads","usage":44.444},{"name":"Scyther","usage":44.444},{"name":"Gyarados","usage":44.444},{"name":"Zarude","usage":44.444},{"name":"Corviknight","usage":44.444},{"name":"Ogerpon","usage":44.444},{"name":"Ampharos","usage":22.222},{"name":"Greninja","usage":11.111},{"name":"Lucario","usage":11.111}],"counters":[],"lead":{"usage":1.51515,"raw":1,"rawp":1.515}},"vaporeon":{"usage":10.60606,"raw":7,"avg":1,"vc":54,"abilities":[{"name":"Regenerator","usage":100}],"moves":[{"name":"Flip Turn","usage":100},{"name":"Dragon Tail","usage":100},{"name":"Scald","usage":100},{"name":"Rapid Spin","usage":100}],"items":[{"name":"Assault Vest","usage":100}],"spreads":[{"nature":"Relaxed","evs":{"hp":252,"atk":0,"def":252,"spa":0,"spd":4,"spe":0},"usage":100}],"teammates":[{"name":"Scream Tail","usage":100},{"name":"Forretress","usage":100},{"name":"Barraskewda","usage":100},{"name":"Jolteon","usage":100},{"name":"Zarude","usage":100}],"counters":[],"lead":{"usage":0,"raw":0,"rawp":0}},"chesnaught":{"usage":10.60606,"raw":7,"avg":1,"vc":64,"abilities":[{"name":"Poison Heal","usage":100}],"moves":[{"name":"Spiky Shield","usage":100},{"name":"U-turn","usage":71.429},{"name":"Spikes","usage":71.429},{"name":"Body Press","usage":71.429},{"name":"Leech Seed","usage":28.571},{"name":"Drain Punch","usage":28.571},{"name":"Synthesis","usage":28.571}],"items":[{"name":"Toxic Orb","usage":100}],"spreads":[{"nature":"Bold","evs":{"hp":252,"atk":0,"def":252,"spa":4,"spd":0,"spe":0},"usage":71.429},{"nature":"Impish","evs":{"hp":252,"atk":4,"def":252,"spa":0,"spd":0,"spe":0},"usage":28.571}],"teammates":[{"name":"Fezandipiti","usage":100},{"name":"Milotic","usage":100},{"name":"Dusknoir","usage":71.429},{"name":"Landorus-Therian","usage":71.429},{"name":"Scream Tail","usage":71.429},{"name":"Hatterene","usage":28.571},{"name":"Chandelure","usage":28.571},{"name":"Haxorus","usage":28.571}],"counters":[],"lead":{"usage":1.51515,"raw":1,"rawp":1.515}},"ogerpon":{"usage":10.60606,"raw":7,"avg":1,"vc":51,"abilities":[{"name":"Contrary","usage":71.429},{"name":"Grassy Surge","usage":28.571}],"moves":[{"name":"Knock Off","usage":71.429},{"name":"Ivy Cudgel","usage":71.429},{"name":"Superpower","usage":71.429},{"name":"Rock Slide","usage":57.143},{"name":"Swords Dance","usage":28.571},{"name":"Grassy Glide","usage":28.571},{"name":"Substitute","usage":28.571},{"name":"Stone Edge","usage":28.571},{"name":"Other","usage":14.286}],"items":[{"name":"Leftovers","usage":100}],"spreads":[{"nature":"Jolly","evs":{"hp":0,"atk":252,"def":0,"spa":0,"spd":4,"spe":252},"usage":100}],"teammates":[{"name":"Fezandipiti","usage":57.143},{"name":"Iron Treads","usage":57.143},{"name":"Scyther","usage":57.143},{"name":"Gengar","usage":57.143},{"name":"Cinderace","usage":57.143},{"name":"Meowscarada","usage":28.571},{"name":"Decidueye-Hisui","usage":28.571},{"name":"Lilligant","usage":28.571},{"name":"Sunflora","usage":28.571},{"name":"Torterra","usage":28.571},{"name":"Tinkaton","usage":14.286}],"counters":[],"lead":{"usage":0,"raw":0,"rawp":0}},"scyther":{"usage":10.60606,"raw":7,"avg":1,"vc":59,"abilities":[{"name":"Compound Eyes","usage":57.143},{"name":"Intimidate","usage":42.857}],"moves":[{"name":"U-turn","usage":100},{"name":"Sticky Web","usage":100},{"name":"Tailwind","usage":57.143},{"name":"Sleep Powder","usage":57.143},{"name":"Roost","usage":42.857},{"name":"Toxic","usage":42.857}],"items":[{"name":"Focus Sash","usage":57.143},{"name":"Eviolite","usage":42.857}],"spreads":[{"nature":"Jolly","evs":{"hp":248,"atk":0,"def":0,"spa":0,"spd":8,"spe":252},"usage":57.143},{"nature":"Careful","evs":{"hp":248,"atk":0,"def":56,"spa":0,"spd":48,"spe":156},"usage":42.857}],"teammates":[{"name":"Gengar","usage":100},{"name":"Fezandipiti","usage":57.143},{"name":"Iron Treads","usage":57.143},{"name":"Ogerpon","usage":57.143},{"name":"Cinderace","usage":57.143},{"name":"Dusclops","usage":42.857},{"name":"Milotic","usage":42.857},{"name":"Flareon","usage":42.857},{"name":"Landorus-Therian","usage":42.857}],"counters":[],"lead":{"usage":10.60606,"raw":7,"rawp":10.606}},"samurotthisui":{"usage":9.09091,"raw":6,"avg":1,"vc":54,"abilities":[{"name":"Adaptability","usage":83.333},{"name":"Sharpness","usage":16.667}],"moves":[{"name":"Ceaseless Edge","usage":100},{"name":"Dragon Dance","usage":100},{"name":"Liquidation","usage":50},{"name":"Sucker Punch","usage":50},{"name":"Crabhammer","usage":33.333},{"name":"Close Combat","usage":33.333},{"name":"Aqua Jet","usage":16.667},{"name":"Other","usage":16.667}],"items":[{"name":"Focus Sash","usage":50},{"name":"Life Orb","usage":50}],"spreads":[{"nature":"Adamant","evs":{"hp":0,"atk":252,"def":0,"spa":0,"spd":4,"spe":252},"usage":100}],"teammates":[{"name":"Landorus-Therian","usage":83.333},{"name":"Haxorus","usage":50},{"name":"Articuno-Galar","usage":50},{"name":"Zarude","usage":50},{"name":"Shaymin","usage":50},{"name":"Scream Tail","usage":50},{"name":"Milotic","usage":33.333},{"name":"Chandelure","usage":33.333},{"name":"Hippowdon","usage":33.333},{"name":"Cinderace","usage":16.667},{"name":"Gyarados","usage":16.667}],"counters":[],"lead":{"usage":1.51515,"raw":1,"rawp":1.515}},"gyarados":{"usage":9.09091,"raw":6,"avg":1,"vc":45,"abilities":[{"name":"Moxie","usage":100}],"moves":[{"name":"Outrage","usage":100},{"name":"Dragon Dance","usage":100},{"name":"Waterfall","usage":100},{"name":"Earthquake","usage":100}],"items":[{"name":"Life Orb","usage":100}],"spreads":[{"nature":"Adamant","evs":{"hp":0,"atk":252,"def":0,"spa":0,"spd":4,"spe":252},"usage":100}],"teammates":[{"name":"Gengar","usage":100},{"name":"Corviknight","usage":100},{"name":"Cinderace","usage":66.667},{"name":"Zarude","usage":66.667},{"name":"Lucario","usage":50},{"name":"Greninja","usage":33.333},{"name":"Ampharos","usage":33.333},{"name":"Garchomp","usage":33.333},{"name":"Garchomp","usage":33.333}],"counters":[],"lead":{"usage":3.0303,"raw":2,"rawp":3.03}},"corviknight":{"usage":9.09091,"raw":6,"avg":1,"vc":45,"abilities":[{"name":"Mirror Armor","usage":100}],"moves":[{"name":"Body Press","usage":100},{"name":"Dual Wingbeat","usage":100},{"name":"Roost","usage":100},{"name":"Iron Defense","usage":100}],"items":[{"name":"Rocky Helmet","usage":100}],"spreads":[{"nature":"Careful","evs":{"hp":248,"atk":8,"def":0,"spa":0,"spd":252,"spe":0},"usage":100}],"teammates":[{"name":"Gyarados","usage":100},{"name":"Gengar","usage":100},{"name":"Cinderace","usage":66.667},{"name":"Zarude","usage":66.667},{"name":"Lucario","usage":50},{"name":"Greninja","usage":33.333},{"name":"Ampharos","usage":33.333},{"name":"Garchomp","usage":33.333},{"name":"Garchomp","usage":33.333}],"counters":[],"lead":{"usage":0,"raw":0,"rawp":0}},"flareon":{"usage":7.57576,"raw":5,"avg":1,"vc":61,"abilities":[{"name":"Drought","usage":80},{"name":"Libero","usage":20}],"moves":[{"name":"Pyro Ball","usage":100},{"name":"Dragon Dance","usage":60},{"name":"Stone Edge","usage":60},{"name":"Earthquake","usage":60},{"name":"Earth Power","usage":20},{"name":"Eruption","usage":20},{"name":"Aerial Ace","usage":20},{"name":"Close Combat","usage":20},{"name":"Trailblaze","usage":20},{"name":"Other","usage":20}],"items":[{"name":"Leftovers","usage":60},{"name":"Focus Sash","usage":20},{"name":"Charcoal","usage":20}],"spreads":[{"nature":"Adamant","evs":{"hp":4,"atk":252,"def":0,"spa":0,"spd":0,"spe":252},"usage":60},{"nature":"Adamant","evs":{"hp":252,"atk":252,"def":0,"spa":0,"spd":4,"spe":0},"usage":20},{"nature":"Quiet","evs":{"hp":4,"atk":252,"def":0,"spa":252,"spd":0,"spe":0},"usage":20}],"teammates":[{"name":"Dusclops","usage":60},{"name":"Milotic","usage":60},{"name":"Scyther","usage":60},{"name":"Landorus-Therian","usage":60},{"name":"Gengar","usage":60},{"name":"Rotom-Fan","usage":20},{"name":"Hatterene","usage":20},{"name":"Crawdaunt","usage":20},{"name":"Hariyama","usage":20},{"name":"Spiritomb","usage":20},{"name":"Ursaluna","usage":20}],"counters":[],"lead":{"usage":1.51515,"raw":1,"rawp":1.515}},"dusknoir":{"usage":7.57576,"raw":5,"avg":1,"vc":64,"abilities":[{"name":"Fluffy","usage":100}],"moves":[{"name":"Foul Play","usage":100},{"name":"Will-O-Wisp","usage":100},{"name":"Strength Sap","usage":100},{"name":"Shadow Sneak","usage":100}],"items":[{"name":"Leftovers","usage":100}],"spreads":[{"nature":"Impish","evs":{"hp":252,"atk":0,"def":252,"spa":0,"spd":4,"spe":0},"usage":100}],"teammates":[{"name":"Scream Tail","usage":100},{"name":"Fezandipiti","usage":100},{"name":"Milotic","usage":100},{"name":"Chesnaught","usage":100},{"name":"Landorus-Therian","usage":100}],"counters":[],"lead":{"usage":0,"raw":0,"rawp":0}},"scizor":{"usage":7.57576,"raw":5,"avg":1,"vc":56,"abilities":[{"name":"Technician","usage":100}],"moves":[{"name":"Bullet Punch","usage":100},{"name":"U-turn","usage":100},{"name":"Rapid Spin","usage":100},{"name":"Stealth Rock","usage":60},{"name":"Rock Blast","usage":40}],"items":[{"name":"Leftovers","usage":40},{"name":"Heavy-Duty Boots","usage":40},{"name":"Rocky Helmet","usage":20}],"spreads":[{"nature":"Adamant","evs":{"hp":252,"atk":252,"def":0,"spa":0,"spd":4,"spe":0},"usage":40},{"nature":"Adamant","evs":{"hp":248,"atk":252,"def":0,"spa":0,"spd":8,"spe":0},"usage":40},{"nature":"Careful","evs":{"hp":0,"atk":216,"def":136,"spa":0,"spd":120,"spe":36},"usage":20}],"teammates":[{"name":"Bisharp","usage":60},{"name":"Oricorio-Sensu","usage":60},{"name":"Floatzel","usage":40},{"name":"Camerupt","usage":40},{"name":"Typhlosion","usage":40},{"name":"Landorus-Therian","usage":40},{"name":"Shaymin","usage":40},{"name":"Snorlax","usage":40},{"name":"Slowbro","usage":40},{"name":"Tauros-Paldea-Aqua","usage":40},{"name":"Milotic","usage":20}],"counters":[],"lead":{"usage":1.51515,"raw":1,"rawp":1.515}},"ursaluna":{"usage":6.06061,"raw":4,"avg":1,"vc":61,"abilities":[{"name":"Guts","usage":100}],"moves":[{"name":"Headlong Rush","usage":100},{"name":"Facade","usage":100},{"name":"Moonlight","usage":75},{"name":"Fire Punch","usage":75},{"name":"Close Combat","usage":25},{"name":"Swords Dance","usage":25}],"items":[{"name":"Flame Orb","usage":100}],"spreads":[{"nature":"Adamant","evs":{"hp":248,"atk":252,"def":0,"spa":0,"spd":8,"spe":0},"usage":75},{"nature":"Brave","evs":{"hp":248,"atk":252,"def":0,"spa":0,"spd":8,"spe":0},"usage":25}],"teammates":[{"name":"Brute Bonnet","usage":100},{"name":"Scream Tail","usage":100},{"name":"Clawitzer","usage":75},{"name":"Glastrier","usage":75},{"name":"Ceruledge","usage":75},{"name":"Hatterene","usage":25},{"name":"Flareon","usage":25},{"name":"Flareon","usage":25}],"counters":[],"lead":{"usage":0,"raw":0,"rawp":0}},"greninja":{"usage":6.06061,"raw":4,"avg":1,"vc":83,"abilities":[{"name":"Adaptability","usage":50},{"name":"Battle Bond","usage":50}],"moves":[{"name":"Dark Pulse","usage":100},{"name":"Nasty Plot","usage":75},{"name":"Surf","usage":50},{"name":"Spikes","usage":50},{"name":"Water Shuriken","usage":50},{"name":"U-turn","usage":25},{"name":"Ice Beam","usage":25},{"name":"Hydro Pump","usage":25}],"items":[{"name":"Wise Glasses","usage":50},{"name":"Loaded Dice","usage":25},{"name":"Choice Specs","usage":25}],"spreads":[{"nature":"Timid","evs":{"hp":0,"atk":0,"def":0,"spa":252,"spd":4,"spe":252},"usage":100}],"teammates":[{"name":"Gengar","usage":50},{"name":"Gyarados","usage":50},{"name":"Garchomp","usage":50},{"name":"Lucario","usage":50},{"name":"Corviknight","usage":50},{"name":"Fezandipiti","usage":25},{"name":"Dipplin","usage":25},{"name":"Cinderace","usage":25},{"name":"Okidogi","usage":25},{"name":"Shaymin","usage":25},{"name":"Umbreon","usage":25}],"counters":[],"lead":{"usage":3.0303,"raw":2,"rawp":3.03}},"florges":{"usage":6.06061,"raw":4,"avg":1,"vc":45,"abilities":[{"name":"Magic Guard","usage":100}],"moves":[{"name":"Thunderbolt","usage":100},{"name":"Flamethrower","usage":100},{"name":"Moonblast","usage":100},{"name":"Synthesis","usage":100}],"items":[{"name":"Life Orb","usage":100}],"spreads":[{"nature":"Modest","evs":{"hp":252,"atk":0,"def":0,"spa":252,"spd":4,"spe":0},"usage":100}],"teammates":[{"name":"Tauros-Paldea-Combat","usage":100},{"name":"Shaymin","usage":100},{"name":"Jolteon","usage":100},{"name":"Haxorus","usage":100},{"name":"Samurott","usage":75},{"name":"Samurott","usage":75}],"counters":[],"lead":{"usage":0,"raw":0,"rawp":0}},"taurospaldeacombat":{"usage":6.06061,"raw":4,"avg":1,"vc":45,"abilities":[{"name":"Sheer Force","usage":100}],"moves":[{"name":"Drain Punch","usage":100},{"name":"Iron Head","usage":100},{"name":"Drill Run","usage":100},{"name":"Ice Punch","usage":100}],"items":[{"name":"Life Orb","usage":100}],"spreads":[{"nature":"Jolly","evs":{"hp":0,"atk":252,"def":0,"spa":0,"spd":4,"spe":252},"usage":100}],"teammates":[{"name":"Haxorus","usage":100},{"name":"Shaymin","usage":100},{"name":"Jolteon","usage":100},{"name":"Florges","usage":100},{"name":"Samurott","usage":75},{"name":"Samurott","usage":75}],"counters":[],"lead":{"usage":0,"raw":0,"rawp":0}},"bisharp":{"usage":6.06061,"raw":4,"avg":1,"vc":56,"abilities":[{"name":"Supreme Overlord","usage":100}],"moves":[{"name":"Swords Dance","usage":100},{"name":"Sucker Punch","usage":100},{"name":"Iron Head","usage":100},{"name":"Kowtow Cleave","usage":50},{"name":"Night Slash","usage":25},{"name":"Low Kick","usage":25}],"items":[{"name":"Eviolite","usage":100}],"spreads":[{"nature":"Adamant","evs":{"hp":252,"atk":252,"def":0,"spa":0,"spd":4,"spe":0},"usage":75},{"nature":"Adamant","evs":{"hp":252,"atk":252,"def":0,"spa":0,"spd":0,"spe":0},"usage":25}],"teammates":[{"name":"Oricorio-Sensu","usage":75},{"name":"Scizor","usage":75},{"name":"Camerupt","usage":50},{"name":"Tauros-Paldea-Aqua","usage":50},{"name":"Floatzel","usage":50},{"name":"Greninja","usage":25},{"name":"Conkeldurr","usage":25},{"name":"Cinderace","usage":25},{"name":"Shaymin","usage":25},{"name":"Dipplin","usage":25},{"name":"Kilowattrel","usage":25}],"counters":[],"lead":{"usage":0,"raw":0,"rawp":0}},"irontreads":{"usage":6.06061,"raw":4,"avg":1,"vc":42,"abilities":[{"name":"Quark Drive","usage":100}],"moves":[{"name":"Iron Head","usage":100},{"name":"Earthquake","usage":100},{"name":"Ice Spinner","usage":100},{"name":"Rapid Spin","usage":100}],"items":[{"name":"Heavy-Duty Boots","usage":100}],"spreads":[{"nature":"Jolly","evs":{"hp":0,"atk":252,"def":0,"spa":0,"spd":4,"spe":252},"usage":100}],"teammates":[{"name":"Fezandipiti","usage":100},{"name":"Cinderace","usage":100},{"name":"Ogerpon","usage":100},{"name":"Gengar","usage":100},{"name":"Scyther","usage":100}],"counters":[],"lead":{"usage":0,"raw":0,"rawp":0}},"dusclops":{"usage":6.06061,"raw":4,"avg":1,"vc":59,"abilities":[{"name":"Fluffy","usage":100}],"moves":[{"name":"Night Shade","usage":100},{"name":"Curse","usage":100},{"name":"Strength Sap","usage":100},{"name":"Will-O-Wisp","usage":75},{"name":"Mean Look","usage":25}],"items":[{"name":"Eviolite","usage":100}],"spreads":[{"nature":"Calm","evs":{"hp":252,"atk":0,"def":4,"spa":0,"spd":252,"spe":0},"usage":100}],"teammates":[{"name":"Milotic","usage":75},{"name":"Flareon","usage":75},{"name":"Scyther","usage":75},{"name":"Landorus-Therian","usage":75},{"name":"Gengar","usage":75},{"name":"Meowscarada","usage":25},{"name":"Toxapex","usage":25},{"name":"Krookodile","usage":25},{"name":"Skeledirge","usage":25},{"name":"Skeledirge","usage":25}],"counters":[],"lead":{"usage":0,"raw":0,"rawp":0}},"brutebonnet":{"usage":6.06061,"raw":4,"avg":1,"vc":61,"abilities":[{"name":"Tablets of Ruin","usage":75},{"name":"Water Absorb","usage":25}],"moves":[{"name":"Trick Room","usage":100},{"name":"Flower Trick","usage":100},{"name":"Swords Dance","usage":75},{"name":"Sucker Punch","usage":75},{"name":"Knock Off","usage":25},{"name":"Explosion","usage":25}],"items":[{"name":"Leftovers","usage":75},{"name":"Focus Sash","usage":25}],"spreads":[{"nature":"Brave","evs":{"hp":252,"atk":252,"def":0,"spa":0,"spd":4,"spe":0},"usage":100}],"teammates":[{"name":"Ursaluna","usage":100},{"name":"Scream Tail","usage":100},{"name":"Clawitzer","usage":75},{"name":"Glastrier","usage":75},{"name":"Ceruledge","usage":75},{"name":"Hatterene","usage":25},{"name":"Flareon","usage":25},{"name":"Flareon","usage":25}],"counters":[],"lead":{"usage":0,"raw":0,"rawp":0}},"ceruledge":{"usage":6.06061,"raw":4,"avg":1,"vc":60,"abilities":[{"name":"Unaware","usage":100}],"moves":[{"name":"Bitter Blade","usage":100},{"name":"Trick Room","usage":75},{"name":"Overheat","usage":75},{"name":"Memento","usage":75},{"name":"Bulk Up","usage":25},{"name":"Slack Off","usage":25},{"name":"Shadow Sneak","usage":25}],"items":[{"name":"Eject Pack","usage":75},{"name":"Clear Amulet","usage":25}],"spreads":[{"nature":"Sassy","evs":{"hp":252,"atk":4,"def":0,"spa":0,"spd":252,"spe":0},"usage":75},{"nature":"Adamant","evs":{"hp":252,"atk":116,"def":60,"spa":0,"spd":12,"spe":68},"usage":25}],"teammates":[{"name":"Clawitzer","usage":75},{"name":"Glastrier","usage":75},{"name":"Brute Bonnet","usage":75},{"name":"Ursaluna","usage":75},{"name":"Scream Tail","usage":75},{"name":"Tinkaton","usage":25},{"name":"Ogerpon","usage":25},{"name":"Alomomola","usage":25},{"name":"Goodra","usage":25},{"name":"Goodra","usage":25}],"counters":[],"lead":{"usage":0,"raw":0,"rawp":0}},"meowscarada":{"usage":4.54545,"raw":3,"avg":1,"vc":51,"abilities":[{"name":"Wind Rider","usage":66.667},{"name":"Tablets of Ruin","usage":33.333}],"moves":[{"name":"Crunch","usage":66.667},{"name":"Tailwind","usage":66.667},{"name":"Flower Trick","usage":66.667},{"name":"Aerial Ace","usage":66.667},{"name":"Dark Pulse","usage":33.333},{"name":"Giga Drain","usage":33.333},{"name":"Hex","usage":33.333},{"name":"Nasty Plot","usage":33.333}],"items":[{"name":"Focus Sash","usage":66.667},{"name":"Leftovers","usage":33.333}],"spreads":[{"nature":"Jolly","evs":{"hp":0,"atk":252,"def":0,"spa":0,"spd":4,"spe":252},"usage":66.667},{"nature":"Timid","evs":{"hp":0,"atk":0,"def":0,"spa":252,"spd":4,"spe":252},"usage":33.333}],"teammates":[{"name":"Decidueye-Hisui","usage":66.667},{"name":"Ogerpon","usage":66.667},{"name":"Lilligant","usage":66.667},{"name":"Sunflora","usage":66.667},{"name":"Torterra","usage":66.667},{"name":"Dusclops","usage":33.333},{"name":"Skeledirge","usage":33.333},{"name":"Toxapex","usage":33.333},{"name":"Scream Tail","usage":33.333},{"name":"Krookodile","usage":33.333}],"counters":[],"lead":{"usage":3.0303,"raw":2,"rawp":3.03}},"clawitzer":{"usage":4.54545,"raw":3,"avg":1,"vc":60,"abilities":[{"name":"Adaptability","usage":100}],"moves":[{"name":"Vacuum Wave","usage":100},{"name":"Boomburst","usage":100},{"name":"Ice Beam","usage":100},{"name":"Surf","usage":66.667},{"name":"Hydro Cannon","usage":33.333}],"items":[{"name":"Throat Spray","usage":100}],"spreads":[{"nature":"Quiet","evs":{"hp":252,"atk":0,"def":0,"spa":252,"spd":4,"spe":0},"usage":100}],"teammates":[{"name":"Scream Tail","usage":100},{"name":"Brute Bonnet","usage":100},{"name":"Ceruledge","usage":100},{"name":"Glastrier","usage":100},{"name":"Ursaluna","usage":100}],"counters":[],"lead":{"usage":0,"raw":0,"rawp":0}},"articunogalar":{"usage":4.54545,"raw":3,"avg":1,"vc":49,"abilities":[{"name":"Tinted Lens","usage":100}],"moves":[{"name":"Calm Mind","usage":100},{"name":"Recover","usage":100},{"name":"Esper Wing","usage":100},{"name":"Air Slash","usage":100}],"items":[{"name":"Leftovers","usage":100}],"spreads":[{"nature":"Timid","evs":{"hp":0,"atk":0,"def":0,"spa":252,"spd":4,"spe":252},"usage":100}],"teammates":[{"name":"Scream Tail","usage":100},{"name":"Landorus-Therian","usage":100},{"name":"Shaymin","usage":100},{"name":"Haxorus","usage":100},{"name":"Samurott-Hisui","usage":100}],"counters":[],"lead":{"usage":0,"raw":0,"rawp":0}},"floatzel":{"usage":4.54545,"raw":3,"avg":1,"vc":56,"abilities":[{"name":"Mega Launcher","usage":66.667},{"name":"Moxie","usage":33.333}],"moves":[{"name":"Dark Pulse","usage":66.667},{"name":"Aura Sphere","usage":66.667},{"name":"Water Pulse","usage":66.667},{"name":"Nasty Plot","usage":66.667},{"name":"Wave Crash","usage":33.333},{"name":"Megahorn","usage":33.333},{"name":"Trailblaze","usage":33.333},{"name":"Earthquake","usage":33.333}],"items":[{"name":"Mystic Water","usage":66.667},{"name":"Expert Belt","usage":33.333}],"spreads":[{"nature":"Timid","evs":{"hp":0,"atk":0,"def":0,"spa":252,"spd":4,"spe":252},"usage":66.667},{"nature":"Jolly","evs":{"hp":0,"atk":252,"def":0,"spa":0,"spd":4,"spe":252},"usage":33.333}],"teammates":[{"name":"Camerupt","usage":66.667},{"name":"Tauros-Paldea-Aqua","usage":66.667},{"name":"Bisharp","usage":66.667},{"name":"Scizor","usage":66.667},{"name":"Oricorio-Sensu","usage":66.667},{"name":"Rotom-Fan","usage":33.333},{"name":"Toedscruel","usage":33.333},{"name":"Flareon","usage":33.333},{"name":"Hariyama","usage":33.333},{"name":"Spiritomb","usage":33.333}],"counters":[],"lead":{"usage":0,"raw":0,"rawp":0}},"hatterene":{"usage":4.54545,"raw":3,"avg":1,"vc":61,"abilities":[{"name":"Magic Bounce","usage":100}],"moves":[{"name":"Teleport","usage":100},{"name":"Mystical Fire","usage":100},{"name":"Moonblast","usage":66.667},{"name":"Psyshock","usage":66.667},{"name":"Trick Room","usage":33.333},{"name":"Misty Explosion","usage":33.333}],"items":[{"name":"Red Card","usage":66.667},{"name":"Focus Sash","usage":33.333}],"spreads":[{"nature":"Modest","evs":{"hp":252,"atk":0,"def":0,"spa":252,"spd":4,"spe":0},"usage":66.667},{"nature":"Quiet","evs":{"hp":252,"atk":0,"def":0,"spa":252,"spd":4,"spe":0},"usage":33.333}],"teammates":[{"name":"Fezandipiti","usage":66.667},{"name":"Haxorus","usage":66.667},{"name":"Chesnaught","usage":66.667},{"name":"Chandelure","usage":66.667},{"name":"Milotic","usage":66.667},{"name":"Flareon","usage":33.333},{"name":"Ursaluna","usage":33.333},{"name":"Brute Bonnet","usage":33.333},{"name":"Scream Tail","usage":33.333},{"name":"Crawdaunt","usage":33.333}],"counters":[],"lead":{"usage":1.51515,"raw":1,"rawp":1.515}},"lucario":{"usage":4.54545,"raw":3,"avg":1,"vc":45,"abilities":[{"name":"Inner Focus","usage":100}],"moves":[{"name":"Swords Dance","usage":100},{"name":"Meteor Mash","usage":100},{"name":"Agility","usage":100},{"name":"Close Combat","usage":100}],"items":[{"name":"Life Orb","usage":100}],"spreads":[{"nature":"Adamant","evs":{"hp":0,"atk":252,"def":0,"spa":0,"spd":4,"spe":252},"usage":100}],"teammates":[{"name":"Gyarados","usage":100},{"name":"Gengar","usage":100},{"name":"Corviknight","usage":100},{"name":"Greninja","usage":66.667},{"name":"Garchomp","usage":66.667},{"name":"Cinderace","usage":33.333},{"name":"Zarude","usage":33.333}],"counters":[],"lead":{"usage":0,"raw":0,"rawp":0}},"samurott":{"usage":4.54545,"raw":3,"avg":1,"vc":45,"abilities":[{"name":"Rock Head","usage":100}],"moves":[{"name":"Flip Turn","usage":100},{"name":"Avalanche","usage":100},{"name":"Wave Crash","usage":100},{"name":"Double-Edge","usage":100}],"items":[{"name":"Assault Vest","usage":100}],"spreads":[{"nature":"Adamant","evs":{"hp":252,"atk":252,"def":0,"spa":0,"spd":4,"spe":0},"usage":100}],"teammates":[{"name":"Tauros-Paldea-Combat","usage":100},{"name":"Shaymin","usage":100},{"name":"Florges","usage":100},{"name":"Haxorus","usage":100},{"name":"Jolteon","usage":100}],"counters":[],"lead":{"usage":1.51515,"raw":1,"rawp":1.515}},"oricoriosensu":{"usage":4.54545,"raw":3,"avg":1,"vc":56,"abilities":[{"name":"Flare Boost","usage":100}],"moves":[{"name":"Agility","usage":100},{"name":"Air Slash","usage":100},{"name":"Thunderbolt","usage":100},{"name":"Revelation Dance","usage":100}],"items":[{"name":"Flame Orb","usage":100}],"spreads":[{"nature":"Modest","evs":{"hp":0,"atk":0,"def":0,"spa":252,"spd":4,"spe":252},"usage":66.667},{"nature":"Modest","evs":{"hp":0,"atk":0,"def":128,"spa":252,"spd":104,"spe":24},"usage":33.333}],"teammates":[{"name":"Bisharp","usage":100},{"name":"Scizor","usage":100},{"name":"Camerupt","usage":66.667},{"name":"Tauros-Paldea-Aqua","usage":66.667},{"name":"Floatzel","usage":66.667},{"name":"Milotic","usage":33.333},{"name":"Conkeldurr","usage":33.333},{"name":"Heracross","usage":33.333}],"counters":[],"lead":{"usage":0,"raw":0,"rawp":0}},"snorlax":{"usage":3.0303,"raw":2,"avg":1,"vc":55,"abilities":[{"name":"Serene Grace","usage":100}],"moves":[{"name":"Tidy Up","usage":100},{"name":"Crunch","usage":100},{"name":"Body Slam","usage":100},{"name":"Soft-Boiled","usage":100}],"items":[{"name":"Leftovers","usage":100}],"spreads":[{"nature":"Careful","evs":{"hp":252,"atk":68,"def":0,"spa":0,"spd":188,"spe":0},"usage":100}],"teammates":[{"name":"Landorus-Therian","usage":100},{"name":"Scizor","usage":100},{"name":"Slowbro","usage":100},{"name":"Shaymin","usage":100},{"name":"Typhlosion","usage":100}],"counters":[],"lead":{"usage":0,"raw":0,"rawp":0}},"slowbro":{"usage":3.0303,"raw":2,"avg":1,"vc":55,"abilities":[{"name":"Regenerator","usage":100}],"moves":[{"name":"Flip Turn","usage":100},{"name":"Surf","usage":100},{"name":"Flamethrower","usage":100},{"name":"Slack Off","usage":100}],"items":[{"name":"Heavy-Duty Boots","usage":100}],"spreads":[{"nature":"Bold","evs":{"hp":248,"atk":0,"def":124,"spa":136,"spd":0,"spe":0},"usage":100}],"teammates":[{"name":"Landorus-Therian","usage":100},{"name":"Scizor","usage":100},{"name":"Snorlax","usage":100},{"name":"Shaymin","usage":100},{"name":"Typhlosion","usage":100}],"counters":[],"lead":{"usage":0,"raw":0,"rawp":0}},"camerupt":{"usage":3.0303,"raw":2,"avg":1,"vc":56,"abilities":[{"name":"Simple","usage":100}],"moves":[{"name":"Flame Charge","usage":100},{"name":"Endure","usage":100},{"name":"Flamethrower","usage":100},{"name":"Earth Power","usage":100}],"items":[{"name":"Weakness Policy","usage":100}],"spreads":[{"nature":"Timid","evs":{"hp":4,"atk":0,"def":0,"spa":252,"spd":0,"spe":252},"usage":100}],"teammates":[{"name":"Bisharp","usage":100},{"name":"Floatzel","usage":100},{"name":"Scizor","usage":100},{"name":"Oricorio-Sensu","usage":100},{"name":"Tauros-Paldea-Aqua","usage":100}],"counters":[],"lead":{"usage":1.51515,"raw":1,"rawp":1.515}},"okidogi":{"usage":3.0303,"raw":2,"avg":1,"vc":83,"abilities":[{"name":"Dry Skin","usage":50},{"name":"Unburden","usage":50}],"moves":[{"name":"Swords Dance","usage":100},{"name":"Close Combat","usage":100},{"name":"Dire Claw","usage":100},{"name":"Acrobatics","usage":50},{"name":"Ice Punch","usage":50}],"items":[{"name":"Leftovers","usage":50},{"name":"Air Balloon","usage":50}],"spreads":[{"nature":"Jolly","evs":{"hp":0,"atk":252,"def":0,"spa":0,"spd":4,"spe":252},"usage":100}],"teammates":[{"name":"Fezandipiti","usage":50},{"name":"Greninja","usage":50},{"name":"Breloom","usage":50},{"name":"Glastrier","usage":50},{"name":"Stonjourner","usage":50},{"name":"Umbreon","usage":50},{"name":"Landorus-Therian","usage":50},{"name":"Garganacl","usage":50},{"name":"Cramorant","usage":50},{"name":"Ribombee","usage":50}],"counters":[],"lead":{"usage":0,"raw":0,"rawp":0}},"garchomp":{"usage":3.0303,"raw":2,"avg":1,"vc":45,"abilities":[{"name":"Rough Skin","usage":100}],"moves":[{"name":"Swords Dance","usage":100},{"name":"Outrage","usage":100},{"name":"Earthquake","usage":100},{"name":"Poison Jab","usage":100}],"items":[{"name":"Scope Lens","usage":100}],"spreads":[{"nature":"Adamant","evs":{"hp":0,"atk":252,"def":0,"spa":0,"spd":4,"spe":252},"usage":100}],"teammates":[{"name":"Gyarados","usage":100},{"name":"Corviknight","usage":100},{"name":"Greninja","usage":100},{"name":"Gengar","usage":100},{"name":"Lucario","usage":100}],"counters":[],"lead":{"usage":0,"raw":0,"rawp":0}},"hippowdon":{"usage":3.0303,"raw":2,"avg":1,"vc":54,"abilities":[{"name":"Stamina","usage":100}],"moves":[{"name":"Stealth Rock","usage":100},{"name":"Slack Off","usage":100},{"name":"Earthquake","usage":100},{"name":"Rapid Spin","usage":100}],"items":[{"name":"Leftovers","usage":100}],"spreads":[{"nature":"Impish","evs":{"hp":252,"atk":4,"def":204,"spa":0,"spd":48,"spe":0},"usage":100}],"teammates":[{"name":"Landorus-Therian","usage":100},{"name":"Chandelure","usage":100},{"name":"Milotic","usage":100},{"name":"Samurott-Hisui","usage":100},{"name":"Zarude","usage":100}],"counters":[],"lead":{"usage":0,"raw":0,"rawp":0}},"ampharos":{"usage":3.0303,"raw":2,"avg":1,"vc":38,"abilities":[{"name":"Levitate","usage":100}],"moves":[{"name":"Calm Mind","usage":100},{"name":"Thunderbolt","usage":100},{"name":"Grass Knot","usage":100},{"name":"Dazzling Gleam","usage":100}],"items":[{"name":"Leftovers","usage":100}],"spreads":[{"nature":"Quiet","evs":{"hp":248,"atk":8,"def":0,"spa":252,"spd":0,"spe":0},"usage":100}],"teammates":[{"name":"Cinderace","usage":100},{"name":"Corviknight","usage":100},{"name":"Gyarados","usage":100},{"name":"Gengar","usage":100},{"name":"Zarude","usage":100}],"counters":[],"lead":{"usage":0,"raw":0,"rawp":0}},"decidueyehisui":{"usage":3.0303,"raw":2,"avg":1,"vc":51,"abilities":[{"name":"Poison Heal","usage":100}],"moves":[{"name":"Close Combat","usage":100},{"name":"Bulk Up","usage":100},{"name":"Thunder Punch","usage":100},{"name":"Leaf Blade","usage":100}],"items":[{"name":"Toxic Orb","usage":100}],"spreads":[{"nature":"Adamant","evs":{"hp":252,"atk":252,"def":0,"spa":0,"spd":4,"spe":0},"usage":100}],"teammates":[{"name":"Sunflora","usage":100},{"name":"Lilligant","usage":100},{"name":"Torterra","usage":100},{"name":"Ogerpon","usage":100},{"name":"Meowscarada","usage":100}],"counters":[],"lead":{"usage":0,"raw":0,"rawp":0}},"lilligant":{"usage":3.0303,"raw":2,"avg":1,"vc":51,"abilities":[{"name":"Contrary","usage":100}],"moves":[{"name":"Leech Seed","usage":100},{"name":"Leaf Storm","usage":100},{"name":"Sleep Powder","usage":100},{"name":"Synthesis","usage":100}],"items":[{"name":"Life Orb","usage":100}],"spreads":[{"nature":"Timid","evs":{"hp":4,"atk":0,"def":0,"spa":252,"spd":0,"spe":252},"usage":100}],"teammates":[{"name":"Sunflora","usage":100},{"name":"Decidueye-Hisui","usage":100},{"name":"Torterra","usage":100},{"name":"Ogerpon","usage":100},{"name":"Meowscarada","usage":100}],"counters":[],"lead":{"usage":0,"raw":0,"rawp":0}},"torterra":{"usage":3.0303,"raw":2,"avg":1,"vc":51,"abilities":[{"name":"Overgrow","usage":100}],"moves":[{"name":"Swords Dance","usage":100},{"name":"Earthquake","usage":100},{"name":"Rock Blast","usage":100},{"name":"Bullet Seed","usage":100}],"items":[{"name":"Loaded Dice","usage":100}],"spreads":[{"nature":"Adamant","evs":{"hp":252,"atk":252,"def":0,"spa":0,"spd":4,"spe":0},"usage":100}],"teammates":[{"name":"Sunflora","usage":100},{"name":"Lilligant","usage":100},{"name":"Ogerpon","usage":100},{"name":"Meowscarada","usage":100},{"name":"Decidueye-Hisui","usage":100}],"counters":[],"lead":{"usage":0,"raw":0,"rawp":0}},"taurospaldeaaqua":{"usage":3.0303,"raw":2,"avg":1,"vc":56,"abilities":[{"name":"Moxie","usage":100}],"moves":[{"name":"Knock Off","usage":100},{"name":"Ice Spinner","usage":100},{"name":"Aqua Step","usage":100},{"name":"Close Combat","usage":100}],"items":[{"name":"Leftovers","usage":100}],"spreads":[{"nature":"Jolly","evs":{"hp":0,"atk":252,"def":0,"spa":0,"spd":4,"spe":252},"usage":100}],"teammates":[{"name":"Scizor","usage":100},{"name":"Floatzel","usage":100},{"name":"Bisharp","usage":100},{"name":"Oricorio-Sensu","usage":100},{"name":"Camerupt","usage":100}],"counters":[],"lead":{"usage":1.51515,"raw":1,"rawp":1.515}},"typhlosion":{"usage":3.0303,"raw":2,"avg":1,"vc":55,"abilities":[{"name":"Drought","usage":100}],"moves":[{"name":"U-turn","usage":100},{"name":"Solar Beam","usage":100},{"name":"Eruption","usage":100},{"name":"Flamethrower","usage":100}],"items":[{"name":"Choice Scarf","usage":100}],"spreads":[{"nature":"Modest","evs":{"hp":0,"atk":0,"def":0,"spa":252,"spd":4,"spe":252},"usage":100}],"teammates":[{"name":"Landorus-Therian","usage":100},{"name":"Scizor","usage":100},{"name":"Snorlax","usage":100},{"name":"Shaymin","usage":100},{"name":"Slowbro","usage":100}],"counters":[],"lead":{"usage":0,"raw":0,"rawp":0}},"sunflora":{"usage":3.0303,"raw":2,"avg":1,"vc":51,"abilities":[{"name":"Contrary","usage":100}],"moves":[{"name":"Morning Sun","usage":100},{"name":"Leech Seed","usage":100},{"name":"Leaf Storm","usage":100},{"name":"Substitute","usage":100}],"items":[{"name":"Life Orb","usage":100}],"spreads":[{"nature":"Calm","evs":{"hp":252,"atk":0,"def":0,"spa":4,"spd":252,"spe":0},"usage":100}],"teammates":[{"name":"Lilligant","usage":100},{"name":"Torterra","usage":100},{"name":"Ogerpon","usage":100},{"name":"Meowscarada","usage":100},{"name":"Decidueye-Hisui","usage":100}],"counters":[],"lead":{"usage":0,"raw":0,"rawp":0}},"toedscruel":{"usage":1.51515,"raw":1,"avg":1,"vc":27,"abilities":[{"name":"Shell Armor","usage":100}],"moves":[{"name":"Energy Ball","usage":100},{"name":"Spikes","usage":100},{"name":"Earth Power","usage":100},{"name":"Hyper Voice","usage":100}],"items":[{"name":"Throat Spray","usage":100}],"spreads":[{"nature":"Timid","evs":{"hp":0,"atk":0,"def":0,"spa":252,"spd":4,"spe":252},"usage":100}],"teammates":[{"name":"Flareon","usage":100},{"name":"Rotom-Fan","usage":100},{"name":"Floatzel","usage":100},{"name":"Hariyama","usage":100},{"name":"Spiritomb","usage":100}],"counters":[],"lead":{"usage":0,"raw":0,"rawp":0}},"rotomfan":{"usage":1.51515,"raw":1,"avg":1,"vc":27,"abilities":[{"name":"Competitive","usage":100}],"moves":[{"name":"Weather Ball","usage":100},{"name":"Hurricane","usage":100},{"name":"Wildbolt Storm","usage":100},{"name":"Revelation Dance","usage":100}],"items":[{"name":"Assault Vest","usage":100}],"spreads":[{"nature":"Timid","evs":{"hp":0,"atk":0,"def":0,"spa":252,"spd":4,"spe":252},"usage":100}],"teammates":[{"name":"Flareon","usage":100},{"name":"Hariyama","usage":100},{"name":"Floatzel","usage":100},{"name":"Toedscruel","usage":100},{"name":"Spiritomb","usage":100}],"counters":[],"lead":{"usage":0,"raw":0,"rawp":0}},"spiritomb":{"usage":1.51515,"raw":1,"avg":1,"vc":27,"abilities":[{"name":"Prankster","usage":100}],"moves":[{"name":"Foul Play","usage":100},{"name":"Shadow Ball","usage":100},{"name":"Rain Dance","usage":100},{"name":"Destiny Bond","usage":100}],"items":[{"name":"Damp Rock","usage":100}],"spreads":[{"nature":"Calm","evs":{"hp":248,"atk":0,"def":0,"spa":8,"spd":252,"spe":0},"usage":100}],"teammates":[{"name":"Flareon","usage":100},{"name":"Rotom-Fan","usage":100},{"name":"Floatzel","usage":100},{"name":"Toedscruel","usage":100},{"name":"Hariyama","usage":100}],"counters":[],"lead":{"usage":0,"raw":0,"rawp":0}},"hariyama":{"usage":1.51515,"raw":1,"avg":1,"vc":27,"abilities":[{"name":"Regenerator","usage":100}],"moves":[{"name":"U-turn","usage":100},{"name":"Defog","usage":100},{"name":"Brick Break","usage":100},{"name":"Fake Out","usage":100}],"items":[{"name":"Heavy-Duty Boots","usage":100}],"spreads":[{"nature":"Adamant","evs":{"hp":252,"atk":252,"def":0,"spa":0,"spd":4,"spe":0},"usage":100}],"teammates":[{"name":"Flareon","usage":100},{"name":"Rotom-Fan","usage":100},{"name":"Floatzel","usage":100},{"name":"Toedscruel","usage":100},{"name":"Spiritomb","usage":100}],"counters":[],"lead":{"usage":0,"raw":0,"rawp":0}},"dipplin":{"usage":1.51515,"raw":1,"avg":1,"vc":50,"abilities":[{"name":"Thick Fat","usage":100}],"moves":[{"name":"Recover","usage":100},{"name":"Tera Blast","usage":100},{"name":"Apple Acid","usage":100},{"name":"Dragon Pulse","usage":100}],"items":[{"name":"Eviolite","usage":100}],"spreads":[{"nature":"Modest","evs":{"hp":252,"atk":0,"def":0,"spa":252,"spd":4,"spe":0},"usage":100}],"teammates":[{"name":"Cinderace","usage":100},{"name":"Shaymin","usage":100},{"name":"Kilowattrel","usage":100},{"name":"Greninja","usage":100},{"name":"Bisharp","usage":100}],"counters":[],"lead":{"usage":0,"raw":0,"rawp":0}},"crawdaunt":{"usage":1.51515,"raw":1,"avg":1,"vc":61,"abilities":[{"name":"Adaptability","usage":100}],"moves":[{"name":"U-turn","usage":100},{"name":"Crabhammer","usage":100},{"name":"Knock Off","usage":100},{"name":"Gunk Shot","usage":100}],"items":[{"name":"Life Orb","usage":100}],"spreads":[{"nature":"Brave","evs":{"hp":252,"atk":252,"def":4,"spa":0,"spd":0,"spe":0},"usage":100}],"teammates":[{"name":"Flareon","usage":100},{"name":"Scream Tail","usage":100},{"name":"Brute Bonnet","usage":100},{"name":"Hatterene","usage":100},{"name":"Ursaluna","usage":100}],"counters":[],"lead":{"usage":0,"raw":0,"rawp":0}},"ribombee":{"usage":1.51515,"raw":1,"avg":1,"vc":36,"abilities":[{"name":"Shield Dust","usage":100}],"moves":[{"name":"Sticky Web","usage":100},{"name":"U-turn","usage":100},{"name":"Stun Spore","usage":100},{"name":"Moonblast","usage":100}],"items":[{"name":"Focus Sash","usage":100}],"spreads":[{"nature":"Timid","evs":{"hp":248,"atk":0,"def":0,"spa":8,"spd":0,"spe":252},"usage":100}],"teammates":[{"name":"Breloom","usage":100},{"name":"Okidogi","usage":100},{"name":"Cramorant","usage":100},{"name":"Glastrier","usage":100},{"name":"Stonjourner","usage":100}],"counters":[],"lead":{"usage":1.51515,"raw":1,"rawp":1.515}},"goodra":{"usage":1.51515,"raw":1,"avg":1,"vc":44,"abilities":[{"name":"Dragon's Maw","usage":100}],"moves":[{"name":"Sludge Bomb","usage":100},{"name":"Dragon Energy","usage":100},{"name":"Thunderbolt","usage":100},{"name":"Dragon Pulse","usage":100}],"items":[{"name":"Choice Scarf","usage":100}],"spreads":[{"nature":"Timid","evs":{"hp":0,"atk":0,"def":0,"spa":252,"spd":4,"spe":252},"usage":100}],"teammates":[{"name":"Tinkaton","usage":100},{"name":"Ceruledge","usage":100},{"name":"Ogerpon","usage":100},{"name":"Alomomola","usage":100},{"name":"Sinistcha","usage":100}],"counters":[],"lead":{"usage":0,"raw":0,"rawp":0}},"alomomola":{"usage":1.51515,"raw":1,"avg":1,"vc":44,"abilities":[{"name":"Regenerator","usage":100}],"moves":[{"name":"Flip Turn","usage":100},{"name":"Wish","usage":100},{"name":"Scald","usage":100},{"name":"Rapid Spin","usage":100}],"items":[{"name":"Heavy-Duty Boots","usage":100}],"spreads":[{"nature":"Relaxed","evs":{"hp":40,"atk":0,"def":252,"spa":0,"spd":216,"spe":0},"usage":100}],"teammates":[{"name":"Tinkaton","usage":100},{"name":"Goodra","usage":100},{"name":"Ceruledge","usage":100},{"name":"Ogerpon","usage":100},{"name":"Sinistcha","usage":100}],"counters":[],"lead":{"usage":0,"raw":0,"rawp":0}},"tinkaton":{"usage":1.51515,"raw":1,"avg":1,"vc":44,"abilities":[{"name":"Prankster","usage":100}],"moves":[{"name":"Gigaton Hammer","usage":100},{"name":"Stealth Rock","usage":100},{"name":"Thunder Wave","usage":100},{"name":"Spikes","usage":100}],"items":[{"name":"Shuca Berry","usage":100}],"spreads":[{"nature":"Adamant","evs":{"hp":252,"atk":112,"def":0,"spa":0,"spd":144,"spe":0},"usage":100}],"teammates":[{"name":"Goodra","usage":100},{"name":"Ceruledge","usage":100},{"name":"Ogerpon","usage":100},{"name":"Alomomola","usage":100},{"name":"Sinistcha","usage":100}],"counters":[],"lead":{"usage":1.51515,"raw":1,"rawp":1.515}},"sinistcha":{"usage":1.51515,"raw":1,"avg":1,"vc":44,"abilities":[{"name":"Heatproof","usage":100}],"moves":[{"name":"Matcha Gotcha","usage":100},{"name":"Calm Mind","usage":100},{"name":"Scald","usage":100},{"name":"Strength Sap","usage":100}],"items":[{"name":"Leftovers","usage":100}],"spreads":[{"nature":"Bold","evs":{"hp":252,"atk":0,"def":196,"spa":0,"spd":60,"spe":0},"usage":100}],"teammates":[{"name":"Tinkaton","usage":100},{"name":"Goodra","usage":100},{"name":"Ceruledge","usage":100},{"name":"Ogerpon","usage":100},{"name":"Alomomola","usage":100}],"counters":[],"lead":{"usage":0,"raw":0,"rawp":0}},"toxapex":{"usage":1.51515,"raw":1,"avg":1,"vc":46,"abilities":[{"name":"Adaptability","usage":100}],"moves":[{"name":"Acid Spray","usage":100},{"name":"Baneful Bunker","usage":100},{"name":"Recover","usage":100},{"name":"Acupressure","usage":100}],"items":[{"name":"Black Sludge","usage":100}],"spreads":[{"nature":"Careful","evs":{"hp":24,"atk":0,"def":232,"spa":0,"spd":252,"spe":0},"usage":100}],"teammates":[{"name":"Scream Tail","usage":100},{"name":"Skeledirge","usage":100},{"name":"Dusclops","usage":100},{"name":"Krookodile","usage":100},{"name":"Meowscarada","usage":100}],"counters":[],"lead":{"usage":0,"raw":0,"rawp":0}},"heracross":{"usage":1.51515,"raw":1,"avg":1,"vc":45,"abilities":[{"name":"Moxie","usage":100}],"moves":[{"name":"U-turn","usage":100},{"name":"Flare Blitz","usage":100},{"name":"First Impression","usage":100},{"name":"Close Combat","usage":100}],"items":[{"name":"Life Orb","usage":100}],"spreads":[{"nature":"Jolly","evs":{"hp":0,"atk":252,"def":4,"spa":0,"spd":0,"spe":252},"usage":100}],"teammates":[{"name":"Scizor","usage":100},{"name":"Conkeldurr","usage":100},{"name":"Milotic","usage":100},{"name":"Bisharp","usage":100},{"name":"Oricorio-Sensu","usage":100}],"counters":[],"lead":{"usage":0,"raw":0,"rawp":0}},"cramorant":{"usage":1.51515,"raw":1,"avg":1,"vc":36,"abilities":[{"name":"Moxie","usage":100}],"moves":[{"name":"Dragon Dance","usage":100},{"name":"Waterfall","usage":100},{"name":"Earthquake","usage":100},{"name":"Brave Bird","usage":100}],"items":[{"name":"Heavy-Duty Boots","usage":100}],"spreads":[{"nature":"Adamant","evs":{"hp":0,"atk":252,"def":0,"spa":0,"spd":4,"spe":252},"usage":100}],"teammates":[{"name":"Breloom","usage":100},{"name":"Okidogi","usage":100},{"name":"Glastrier","usage":100},{"name":"Stonjourner","usage":100},{"name":"Ribombee","usage":100}],"counters":[],"lead":{"usage":0,"raw":0,"rawp":0}},"krookodile":{"usage":1.51515,"raw":1,"avg":1,"vc":46,"abilities":[{"name":"Vessel of Ruin","usage":100}],"moves":[{"name":"Hone Claws","usage":100},{"name":"Heavy Slam","usage":100},{"name":"Stone Edge","usage":100},{"name":"Earthquake","usage":100}],"items":[{"name":"Leftovers","usage":100}],"spreads":[{"nature":"Jolly","evs":{"hp":0,"atk":252,"def":0,"spa":0,"spd":4,"spe":252},"usage":100}],"teammates":[{"name":"Scream Tail","usage":100},{"name":"Skeledirge","usage":100},{"name":"Toxapex","usage":100},{"name":"Dusclops","usage":100},{"name":"Meowscarada","usage":100}],"counters":[],"lead":{"usage":0,"raw":0,"rawp":0}},"skeledirge":{"usage":1.51515,"raw":1,"avg":1,"vc":46,"abilities":[{"name":"Flame Body","usage":100}],"moves":[{"name":"Swords Dance","usage":100},{"name":"Poltergeist","usage":100},{"name":"Bitter Blade","usage":100},{"name":"Slack Off","usage":100}],"items":[{"name":"Leftovers","usage":100}],"spreads":[{"nature":"Relaxed","evs":{"hp":252,"atk":0,"def":136,"spa":0,"spd":120,"spe":0},"usage":100}],"teammates":[{"name":"Scream Tail","usage":100},{"name":"Toxapex","usage":100},{"name":"Dusclops","usage":100},{"name":"Krookodile","usage":100},{"name":"Meowscarada","usage":100}],"counters":[],"lead":{"usage":0,"raw":0,"rawp":0}},"stonjourner":{"usage":1.51515,"raw":1,"avg":1,"vc":36,"abilities":[{"name":"Rock Head","usage":100}],"moves":[{"name":"Heavy Slam","usage":100},{"name":"Earthquake","usage":100},{"name":"Heat Crash","usage":100},{"name":"Head Smash","usage":100}],"items":[{"name":"Choice Scarf","usage":100}],"spreads":[{"nature":"Adamant","evs":{"hp":0,"atk":252,"def":0,"spa":0,"spd":4,"spe":252},"usage":100}],"teammates":[{"name":"Breloom","usage":100},{"name":"Okidogi","usage":100},{"name":"Cramorant","usage":100},{"name":"Glastrier","usage":100},{"name":"Ribombee","usage":100}],"counters":[],"lead":{"usage":0,"raw":0,"rawp":0}},"garganacl":{"usage":1.51515,"raw":1,"avg":1,"vc":83,"abilities":[{"name":"Regenerator","usage":100}],"moves":[{"name":"Stealth Rock","usage":100},{"name":"Knock Off","usage":100},{"name":"Rapid Spin","usage":100},{"name":"Salt Cure","usage":100}],"items":[{"name":"Leftovers","usage":100}],"spreads":[{"nature":"Careful","evs":{"hp":252,"atk":0,"def":4,"spa":0,"spd":252,"spe":0},"usage":100}],"teammates":[{"name":"Landorus-Therian","usage":100},{"name":"Fezandipiti","usage":100},{"name":"Okidogi","usage":100},{"name":"Greninja","usage":100},{"name":"Umbreon","usage":100}],"counters":[],"lead":{"usage":0,"raw":0,"rawp":0}},"kilowattrel":{"usage":1.51515,"raw":1,"avg":1,"vc":50,"abilities":[{"name":"Volt Absorb","usage":100}],"moves":[{"name":"Air Slash","usage":100},{"name":"Thunderbolt","usage":100},{"name":"Tera Blast","usage":100},{"name":"Nasty Plot","usage":100}],"items":[{"name":"Life Orb","usage":100}],"spreads":[{"nature":"Timid","evs":{"hp":0,"atk":0,"def":0,"spa":252,"spd":4,"spe":252},"usage":100}],"teammates":[{"name":"Cinderace","usage":100},{"name":"Shaymin","usage":100},{"name":"Greninja","usage":100},{"name":"Bisharp","usage":100},{"name":"Dipplin","usage":100}],"counters":[],"lead":{"usage":0,"raw":0,"rawp":0}},"breloom":{"usage":1.51515,"raw":1,"avg":1,"vc":36,"abilities":[{"name":"Technician","usage":100}],"moves":[{"name":"Belly Drum","usage":100},{"name":"Mach Punch","usage":100},{"name":"Bullet Seed","usage":100},{"name":"Rock Tomb","usage":100}],"items":[{"name":"Sitrus Berry","usage":100}],"spreads":[{"nature":"Jolly","evs":{"hp":4,"atk":252,"def":0,"spa":0,"spd":0,"spe":252},"usage":100}],"teammates":[{"name":"Cramorant","usage":100},{"name":"Okidogi","usage":100},{"name":"Glastrier","usage":100},{"name":"Stonjourner","usage":100},{"name":"Ribombee","usage":100}],"counters":[],"lead":{"usage":0,"raw":0,"rawp":0}},"umbreon":{"usage":1.51515,"raw":1,"avg":1,"vc":83,"abilities":[{"name":"Fur Coat","usage":100}],"moves":[{"name":"Foul Play","usage":100},{"name":"Wish","usage":100},{"name":"Protect","usage":100},{"name":"Parting Shot","usage":100}],"items":[{"name":"Leftovers","usage":100}],"spreads":[{"nature":"Relaxed","evs":{"hp":252,"atk":0,"def":252,"spa":0,"spd":4,"spe":0},"usage":100}],"teammates":[{"name":"Landorus-Therian","usage":100},{"name":"Garganacl","usage":100},{"name":"Fezandipiti","usage":100},{"name":"Greninja","usage":100},{"name":"Okidogi","usage":100}],"counters":[],"lead":{"usage":0,"raw":0,"rawp":0}}}