{"battles":41,"avg":1,"pokemon":[{"name":"Chansey","usage":32.92683,"raw":27,"rawp":32.927,"real":23,"realp":35.751},{"name":"Giratina","usage":31.70732,"raw":26,"rawp":31.707,"real":24,"realp":37.306},{"name":"Blissey","usage":29.26829,"raw":24,"rawp":29.268,"real":16,"realp":24.87},{"name":"Regigigas","usage":23.17073,"raw":19,"rawp":23.171,"real":17,"realp":26.425},{"name":"Zacian-Crowned","usage":20.73171,"raw":17,"rawp":20.732,"real":10,"realp":15.544},{"name":"Mewtwo-Mega-X","usage":18.29268,"raw":15,"rawp":18.293,"real":8,"realp":12.435},{"name":"Miraidon","usage":15.85366,"raw":13,"rawp":15.854,"real":9,"realp":13.99},{"name":"Regieleki","usage":14.63415,"raw":12,"rawp":14.634,"real":11,"realp":17.098},{"name":"Ho-Oh","usage":14.63415,"raw":12,"rawp":14.634,"real":11,"realp":17.098},{"name":"Xerneas","usage":13.41463,"raw":11,"rawp":13.415,"real":10,"realp":15.544},{"name":"Shuckle","usage":12.19512,"raw":10,"rawp":12.195,"real":8,"realp":12.435},{"name":"Dondozo","usage":10.97561,"raw":9,"rawp":10.976,"real":8,"realp":12.435},{"name":"Ting-Lu","usage":10.97561,"raw":9,"rawp":10.976,"real":8,"realp":12.435},{"name":"Arceus-Dark","usage":10.97561,"raw":9,"rawp":10.976,"real":7,"realp":10.881},{"name":"Melmetal","usage":10.97561,"raw":9,"rawp":10.976,"real":8,"realp":12.435},{"name":"Mewtwo-Mega-Y","usage":10.97561,"raw":9,"rawp":10.976,"real":4,"realp":6.218},{"name":"Kartana","usage":10.97561,"raw":9,"rawp":10.976,"real":7,"realp":10.881},{"name":"Gyarados-Mega","usage":9.7561,"raw":8,"rawp":9.756,"real":7,"realp":10.881},{"name":"Slaking","usage":8.53659,"raw":7,"rawp":8.537,"real":6,"realp":9.326},{"name":"Zamazenta-Crowned","usage":8.53659,"raw":7,"rawp":8.537,"real":4,"realp":6.218},{"name":"Dialga-Origin","usage":8.53659,"raw":7,"rawp":8.537,"real":7,"realp":10.881},{"name":"Arceus-Water","usage":8.53659,"raw":7,"rawp":8.537,"real":3,"realp":4.663},{"name":"Deoxys-Attack","usage":7.31707,"raw":6,"rawp":7.317,"real":6,"realp":9.326},{"name":"Slowbro-Mega","usage":7.31707,"raw":6,"rawp":7.317,"real":4,"realp":6.218},{"name":"Guzzlord","usage":7.31707,"raw":6,"rawp":7.317,"real":4,"realp":6.218},{"name":"Zygarde","usage":7.31707,"raw":6,"rawp":7.317,"real":3,"realp":4.663},{"name":"Cramorant-Gulping","usage":7.31707,"raw":6,"rawp":7.317,"real":6,"realp":9.326},{"name":"Arceus-Ground","usage":7.31707,"raw":6,"rawp":7.317,"real":4,"realp":6.218},{"name":"Arceus-Steel","usage":7.31707,"raw":6,"rawp":7.317,"real":4,"realp":6.218},{"name":"Diancie-Mega","usage":7.31707,"raw":6,"rawp":7.317,"real":6,"realp":9.326},{"name":"Palafin","usage":7.31707,"raw":6,"rawp":7.317,"real":6,"realp":9.326},{"name":"Kyurem-Black","usage":6.09756,"raw":5,"rawp":6.098,"real":5,"realp":7.772},{"name":"Chien-Pao","usage":6.09756,"raw":5,"rawp":6.098,"real":4,"realp":6.218},{"name":"Giratina-Origin","usage":6.09756,"raw":5,"rawp":6.098,"real":5,"realp":7.772},{"name":"Necrozma-Dawn-Wings","usage":6.09756,"raw":5,"rawp":6.098,"real":3,"realp":4.663},{"name":"Palkia-Origin","usage":4.87805,"raw":4,"rawp":4.878,"real":4,"realp":6.218},{"name":"Cresselia","usage":4.87805,"raw":4,"rawp":4.878,"real":3,"realp":4.663},{"name":"Magearna","usage":4.87805,"raw":4,"rawp":4.878,"real":2,"realp":3.109},{"name":"Calyrex-Ice","usage":4.87805,"raw":4,"rawp":4.878,"real":4,"realp":6.218},{"name":"Eternatus","usage":4.87805,"raw":4,"rawp":4.878,"real":4,"realp":6.218},{"name":"Wo-Chien","usage":4.87805,"raw":4,"rawp":4.878,"real":2,"realp":3.109},{"name":"Porygon2","usage":4.87805,"raw":4,"rawp":4.878,"real":4,"realp":6.218},{"name":"Steelix-Mega","usage":4.87805,"raw":4,"rawp":4.878,"real":4,"realp":6.218},{"name":"Yveltal","usage":4.87805,"raw":4,"rawp":4.878,"real":3,"realp":4.663},{"name":"Zapdos","usage":4.87805,"raw":4,"rawp":4.878,"real":1,"realp":1.554},{"name":"Iron Leaves","usage":3.65854,"raw":3,"rawp":3.659,"real":3,"realp":4.663},{"name":"Arceus","usage":3.65854,"raw":3,"rawp":3.659,"real":3,"realp":4.663},{"name":"Muk-Alola","usage":3.65854,"raw":3,"rawp":3.659,"real":3,"realp":4.663},{"name":"Wishiwashi-School","usage":3.65854,"raw":3,"rawp":3.659,"real":3,"realp":4.663},{"name":"Scream Tail","usage":3.65854,"raw":3,"rawp":3.659,"real":3,"realp":4.663},{"name":"Aggron-Mega","usage":3.65854,"raw":3,"rawp":3.659,"real":3,"realp":4.663},{"name":"Blaziken-Mega","usage":3.65854,"raw":3,"rawp":3.659,"real":2,"realp":3.109},{"name":"Espathra","usage":3.65854,"raw":3,"rawp":3.659,"real":1,"realp":1.554},{"name":"Gengar-Mega","usage":3.65854,"raw":3,"rawp":3.659,"real":2,"realp":3.109},{"name":"Arceus-Ghost","usage":3.65854,"raw":3,"rawp":3.659,"real":3,"realp":4.663},{"name":"Iron Bundle","usage":3.65854,"raw":3,"rawp":3.659,"real":2,"realp":3.109},{"name":"Zoroark-Hisui","usage":3.65854,"raw":3,"rawp":3.659,"real":3,"realp":4.663},{"name":"Deoxys-Defense","usage":3.65854,"raw":3,"rawp":3.659,"real":3,"realp":4.663},{"name":"Arceus-Poison","usage":3.65854,"raw":3,"rawp":3.659,"real":3,"realp":4.663},{"name":"Regice","usage":3.65854,"raw":3,"rawp":3.659,"real":2,"realp":3.109},{"name":"Corviknight","usage":3.65854,"raw":3,"rawp":3.659,"real":3,"realp":4.663},{"name":"Groudon-Primal","usage":3.65854,"raw":3,"rawp":3.659,"real":2,"realp":3.109},{"name":"Sceptile-Mega","usage":3.65854,"raw":3,"rawp":3.659,"real":1,"realp":1.554},{"name":"Swampert-Mega","usage":3.65854,"raw":3,"rawp":3.659,"real":2,"realp":3.109},{"name":"Skarmory","usage":3.65854,"raw":3,"rawp":3.659,"real":3,"realp":4.663},{"name":"Iron Moth","usage":3.65854,"raw":3,"rawp":3.659,"real":2,"realp":3.109},{"name":"Xurkitree","usage":2.43902,"raw":2,"rawp":2.439,"real":1,"realp":1.554},{"name":"Urshifu","usage":2.43902,"raw":2,"rawp":2.439,"real":2,"realp":3.109},{"name":"Lunala","usage":2.43902,"raw":2,"rawp":2.439,"real":2,"realp":3.109},{"name":"Flutter Mane","usage":2.43902,"raw":2,"rawp":2.439,"real":2,"realp":3.109},{"name":"Rattata","usage":2.43902,"raw":2,"rawp":2.439,"real":2,"realp":3.109},{"name":"Charizard-Mega-Y","usage":2.43902,"raw":2,"rawp":2.439,"real":0,"realp":0},{"name":"Pheromosa","usage":2.43902,"raw":2,"rawp":2.439,"real":2,"realp":3.109},{"name":"Dialga","usage":2.43902,"raw":2,"rawp":2.439,"real":1,"realp":1.554},{"name":"Thundurus-Therian","usage":2.43902,"raw":2,"rawp":2.439,"real":2,"realp":3.109},{"name":"Lugia","usage":2.43902,"raw":2,"rawp":2.439,"real":1,"realp":1.554},{"name":"Clodsire","usage":2.43902,"raw":2,"rawp":2.439,"real":2,"realp":3.109},{"name":"Salamence-Mega","usage":2.43902,"raw":2,"rawp":2.439,"real":1,"realp":1.554},{"name":"Barraskewda","usage":1.21951,"raw":1,"rawp":1.22,"real":1,"realp":1.554},{"name":"Necrozma-Dusk-Mane","usage":1.21951,"raw":1,"rawp":1.22,"real":1,"realp":1.554},{"name":"Groudon","usage":1.21951,"raw":1,"rawp":1.22,"real":1,"realp":1.554},{"name":"Hoopa-Unbound","usage":1.21951,"raw":1,"rawp":1.22,"real":0,"realp":0},{"name":"Meloetta","usage":1.21951,"raw":1,"rawp":1.22,"real":0,"realp":0},{"name":"Marshadow","usage":1.21951,"raw":1,"rawp":1.22,"real":1,"realp":1.554},{"name":"Kangaskhan-Mega","usage":1.21951,"raw":1,"rawp":1.22,"real":1,"realp":1.554},{"name":"Goodra-Hisui","usage":1.21951,"raw":1,"rawp":1.22,"real":1,"realp":1.554},{"name":"Dragapult","usage":1.21951,"raw":1,"rawp":1.22,"real":1,"realp":1.554},{"name":"Kyogre-Primal","usage":1.21951,"raw":1,"rawp":1.22,"real":0,"realp":0},{"name":"Ursaluna","usage":1.21951,"raw":1,"rawp":1.22,"real":1,"realp":1.554},{"name":"Chi-Yu","usage":1.21951,"raw":1,"rawp":1.22,"real":1,"realp":1.554}]}